{
	"cells": [
		{
			"id": 540,
			"tex": "(18)",
			"content": [
				"(18)"
			],
			"start_row": 54,
			"end_row": 54,
			"start_col": 6,
			"end_col": 6
		},
		{
			"id": 541,
			"tex": "343",
			"content": [
				"343"
			],
			"start_row": 54,
			"end_row": 54,
			"start_col": 7,
			"end_col": 7
		},
		{
			"id": 542,
			"tex": "0",
			"content": [
				"0"
			],
			"start_row": 54,
			"end_row": 54,
			"start_col": 8,
			"end_col": 8
		},
		{
			"id": 543,
			"tex": "(18)",
			"content": [
				"(18)"
			],
			"start_row": 54,
			"end_row": 54,
			"start_col": 9,
			"end_col": 9
		},
		{
			"id": 544,
			"tex": "san200-0.9-1",
			"content": [
				"san200-0.9-1"
			],
			"start_row": 55,
			"end_row": 55,
			"start_col": 0,
			"end_col": 0
		},
		{
			"id": 545,
			"tex": "981",
			"content": [
				"981"
			],
			"start_row": 55,
			"end_row": 55,
			"start_col": 1,
			"end_col": 1
		},
		{
			"id": 546,
			"tex": "0",
			"content": [
				"0"
			],
			"start_row": 55,
			"end_row": 55,
			"start_col": 2,
			"end_col": 2
		},
		{
			"id": 547,
			"tex": "(70)",
			"content": [
				"(70)"
			],
			"start_row": 55,
			"end_row": 55,
			"start_col": 3,
			"end_col": 3
		},
		{
			"id": 548,
			"tex": "87329",
			"content": [
				"87329"
			],
			"start_row": 55,
			"end_row": 55,
			"start_col": 4,
			"end_col": 4
		},
		{
			"id": 549,
			"tex": "1",
			"content": [
				"1"
			],
			"start_row": 55,
			"end_row": 55,
			"start_col": 5,
			"end_col": 5
		},
		{
			"id": 550,
			"tex": "(70)",
			"content": [
				"(70)"
			],
			"start_row": 55,
			"end_row": 55,
			"start_col": 6,
			"end_col": 6
		},
		{
			"id": 551,
			"tex": "74",
			"content": [
				"74"
			],
			"start_row": 55,
			"end_row": 55,
			"start_col": 7,
			"end_col": 7
		},
		{
			"id": 552,
			"tex": "0",
			"content": [
				"0"
			],
			"start_row": 55,
			"end_row": 55,
			"start_col": 8,
			"end_col": 8
		},
		{
			"id": 553,
			"tex": "(70)",
			"content": [
				"(70)"
			],
			"start_row": 55,
			"end_row": 55,
			"start_col": 9,
			"end_col": 9
		},
		{
			"id": 554,
			"tex": "san200-0.9-2",
			"content": [
				"san200-0.9-2"
			],
			"start_row": 56,
			"end_row": 56,
			"start_col": 0,
			"end_col": 0
		},
		{
			"id": 555,
			"tex": "1,149,564",
			"content": [
				"1,149,564"
			],
			"start_row": 56,
			"end_row": 56,
			"start_col": 1,
			"end_col": 1
		},
		{
			"id": 556,
			"tex": "20",
			"content": [
				"20"
			],
			"start_row": 56,
			"end_row": 56,
			"start_col": 2,
			"end_col": 2
		},
		{
			"id": 557,
			"tex": "(60)",
			"content": [
				"(60)"
			],
			"start_row": 56,
			"end_row": 56,
			"start_col": 3,
			"end_col": 3
		},
		{
			"id": 558,
			"tex": "229,567",
			"content": [
				"229,567"
			],
			"start_row": 56,
			"end_row": 56,
			"start_col": 4,
			"end_col": 4
		},
		{
			"id": 559,
			"tex": "5",
			"content": [
				"5"
			],
			"start_row": 56,
			"end_row": 56,
			"start_col": 5,
			"end_col": 5
		},
		{
			"id": 560,
			"tex": "(60)",
			"content": [
				"(60)"
			],
			"start_row": 56,
			"end_row": 56,
			"start_col": 6,
			"end_col": 6
		},
		{
			"id": 561,
			"tex": "62,776",
			"content": [
				"62,776"
			],
			"start_row": 56,
			"end_row": 56,
			"start_col": 7,
			"end_col": 7
		},
		{
			"id": 562,
			"tex": "\\bf{1}",
			"content": [
				"1"
			],
			"start_row": 56,
			"end_row": 56,
			"start_col": 8,
			"end_col": 8
		},
		{
			"id": 563,
			"tex": "(60)",
			"content": [
				"(60)"
			],
			"start_row": 56,
			"end_row": 56,
			"start_col": 9,
			"end_col": 9
		},
		{
			"id": 564,
			"tex": "san200-0.9-3",
			"content": [
				"san200-0.9-3"
			],
			"start_row": 57,
			"end_row": 57,
			"start_col": 0,
			"end_col": 0
		},
		{
			"id": 565,
			"tex": "8,260,345",
			"content": [
				"8,260,345"
			],
			"start_row": 57,
			"end_row": 57,
			"start_col": 1,
			"end_col": 1
		},
		{
			"id": 566,
			"tex": "154",
			"content": [
				"154"
			],
			"start_row": 57,
			"end_row": 57,
			"start_col": 2,
			"end_col": 2
		},
		{
			"id": 567,
			"tex": "(44)",
			"content": [
				"(44)"
			],
			"start_row": 57,
			"end_row": 57,
			"start_col": 3,
			"end_col": 3
		},
		{
			"id": 568,
			"tex": "6,815,145",
			"content": [
				"6,815,145"
			],
			"start_row": 57,
			"end_row": 57,
			"start_col": 4,
			"end_col": 4
		},
		{
			"id": 569,
			"tex": "111",
			"content": [
				"111"
			],
			"start_row": 57,
			"end_row": 57,
			"start_col": 5,
			"end_col": 5
		},
		{
			"id": 570,
			"tex": "(44)",
			"content": [
				"(44)"
			],
			"start_row": 57,
			"end_row": 57,
			"start_col": 6,
			"end_col": 6
		},
		{
			"id": 571,
			"tex": "1,218,317",
			"content": [
				"1,218,317"
			],
			"start_row": 57,
			"end_row": 57,
			"start_col": 7,
			"end_col": 7
		},
		{
			"id": 572,
			"tex": "\\bf{32}",
			"content": [
				"32"
			],
			"start_row": 57,
			"end_row": 57,
			"start_col": 8,
			"end_col": 8
		},
		{
			"id": 573,
			"tex": "(44)",
			"content": [
				"(44)"
			],
			"start_row": 57,
			"end_row": 57,
			"start_col": 9,
			"end_col": 9
		},
		{
			"id": 574,
			"tex": "san400-0.5-1",
			"content": [
				"san400-0.5-1"
			],
			"start_row": 58,
			"end_row": 58,
			"start_col": 0,
			"end_col": 0
		},
		{
			"id": 575,
			"tex": "3,960",
			"content": [
				"3,960"
			],
			"start_row": 58,
			"end_row": 58,
			"start_col": 1,
			"end_col": 1
		},
		{
			"id": 576,
			"tex": "0",
			"content": [
				"0"
			],
			"start_row": 58,
			"end_row": 58,
			"start_col": 2,
			"end_col": 2
		},
		{
			"id": 577,
			"tex": "(13)",
			"content": [
				"(13)"
			],
			"start_row": 58,
			"end_row": 58,
			"start_col": 3,
			"end_col": 3
		},
		{
			"id": 578,
			"tex": "2,453",
			"content": [
				"2,453"
			],
			"start_row": 58,
			"end_row": 58,
			"start_col": 4,
			"end_col": 4
		},
		{
			"id": 579,
			"tex": "0",
			"content": [
				"0"
			],
			"start_row": 58,
			"end_row": 58,
			"start_col": 5,
			"end_col": 5
		},
		{
			"id": 580,
			"tex": "(13)",
			"content": [
				"(13)"
			],
			"start_row": 58,
			"end_row": 58,
			"start_col": 6,
			"end_col": 6
		},
		{
			"id": 581,
			"tex": "1,386",
			"content": [
				"1,386"
			],
			"start_row": 58,
			"end_row": 58,
			"start_col": 7,
			"end_col": 7
		},
		{
			"id": 582,
			"tex": "0",
			"content": [
				"0"
			],
			"start_row": 58,
			"end_row": 58,
			"start_col": 8,
			"end_col": 8
		},
		{
			"id": 583,
			"tex": "(13)",
			"content": [
				"(13)"
			],
			"start_row": 58,
			"end_row": 58,
			"start_col": 9,
			"end_col": 9
		},
		{
			"id": 584,
			"tex": "san400-0.7-1",
			"content": [
				"san400-0.7-1"
			],
			"start_row": 59,
			"end_row": 59,
			"start_col": 0,
			"end_col": 0
		},
		{
			"id": 585,
			"tex": "55,010",
			"content": [
				"55,010"
			],
			"start_row": 59,
			"end_row": 59,
			"start_col": 1,
			"end_col": 1
		},
		{
			"id": 586,
			"tex": "\\bf{1}",
			"content": [
				"1"
			],
			"start_row": 59,
			"end_row": 59,
			"start_col": 2,
			"end_col": 2
		},
		{
			"id": 587,
			"tex": "(40)",
			"content": [
				"(40)"
			],
			"start_row": 59,
			"end_row": 59,
			"start_col": 3,
			"end_col": 3
		},
		{
			"id": 588,
			"tex": "119,356",
			"content": [
				"119,356"
			],
			"start_row": 59,
			"end_row": 59,
			"start_col": 4,
			"end_col": 4
		},
		{
			"id": 589,
			"tex": "2",
			"content": [
				"2"
			],
			"start_row": 59,
			"end_row": 59,
			"start_col": 5,
			"end_col": 5
		},
		{
			"id": 590,
			"tex": "(40)",
			"content": [
				"(40)"
			],
			"start_row": 59,
			"end_row": 59,
			"start_col": 6,
			"end_col": 6
		},
		{
			"id": 591,
			"tex": "134,772",
			"content": [
				"134,772"
			],
			"start_row": 59,
			"end_row": 59,
			"start_col": 7,
			"end_col": 7
		},
		{
			"id": 592,
			"tex": "3",
			"content": [
				"3"
			],
			"start_row": 59,
			"end_row": 59,
			"start_col": 8,
			"end_col": 8
		},
		{
			"id": 593,
			"tex": "(40)",
			"content": [
				"(40)"
			],
			"start_row": 59,
			"end_row": 59,
			"start_col": 9,
			"end_col": 9
		},
		{
			"id": 594,
			"tex": "san400-0.7-2",
			"content": [
				"san400-0.7-2"
			],
			"start_row": 60,
			"end_row": 60,
			"start_col": 0,
			"end_col": 0
		},
		{
			"id": 595,
			"tex": "606,159",
			"content": [
				"606,159"
			],
			"start_row": 60,
			"end_row": 60,
			"start_col": 1,
			"end_col": 1
		},
		{
			"id": 596,
			"tex": "\\bf{14}",
			"content": [
				"14"
			],
			"start_row": 60,
			"end_row": 60,
			"start_col": 2,
			"end_col": 2
		},
		{
			"id": 597,
			"tex": "(30)",
			"content": [
				"(30)"
			],
			"start_row": 60,
			"end_row": 60,
			"start_col": 3,
			"end_col": 3
		},
		{
			"id": 598,
			"tex": "889,125",
			"content": [
				"889,125"
			],
			"start_row": 60,
			"end_row": 60,
			"start_col": 4,
			"end_col": 4
		},
		{
			"id": 599,
			"tex": "19",
			"content": [
				"19"
			],
			"start_row": 60,
			"end_row": 60,
			"start_col": 5,
			"end_col": 5
		},
		{
			"id": 600,
			"tex": "(30)",
			"content": [
				"(30)"
			],
			"start_row": 60,
			"end_row": 60,
			"start_col": 6,
			"end_col": 6
		},
		{
			"id": 601,
			"tex": "754,146",
			"content": [
				"754,146"
			],
			"start_row": 60,
			"end_row": 60,
			"start_col": 7,
			"end_col": 7
		},
		{
			"id": 602,
			"tex": "16",
			"content": [
				"16"
			],
			"start_row": 60,
			"end_row": 60,
			"start_col": 8,
			"end_col": 8
		},
		{
			"id": 603,
			"tex": "(30)",
			"content": [
				"(30)"
			],
			"start_row": 60,
			"end_row": 60,
			"start_col": 9,
			"end_col": 9
		},
		{
			"id": 604,
			"tex": "san400-0.7-3",
			"content": [
				"san400-0.7-3"
			],
			"start_row": 61,
			"end_row": 61,
			"start_col": 0,
			"end_col": 0
		},
		{
			"id": 605,
			"tex": "582,646",
			"content": [
				"582,646"
			],
			"start_row": 61,
			"end_row": 61,
			"start_col": 1,
			"end_col": 1
		},
		{
			"id": 606,
			"tex": "11",
			"content": [
				"11"
			],
			"start_row": 61,
			"end_row": 61,
			"start_col": 2,
			"end_col": 2
		},
		{
			"id": 607,
			"tex": "(22)",
			"content": [
				"(22)"
			],
			"start_row": 61,
			"end_row": 61,
			"start_col": 3,
			"end_col": 3
		},
		{
			"id": 608,
			"tex": "521,410",
			"content": [
				"521,410"
			],
			"start_row": 61,
			"end_row": 61,
			"start_col": 4,
			"end_col": 4
		},
		{
			"id": 609,
			"tex": "10",
			"content": [
				"10"
			],
			"start_row": 61,
			"end_row": 61,
			"start_col": 5,
			"end_col": 5
		},
		{
			"id": 610,
			"tex": "(22)",
			"content": [
				"(22)"
			],
			"start_row": 61,
			"end_row": 61,
			"start_col": 6,
			"end_col": 6
		},
		{
			"id": 611,
			"tex": "215,785",
			"content": [
				"215,785"
			],
			"start_row": 61,
			"end_row": 61,
			"start_col": 7,
			"end_col": 7
		},
		{
			"id": 323,
			"tex": "\\bf{(54)}",
			"content": [
				"(54)"
			],
			"start_row": 32,
			"end_row": 32,
			"start_col": 9,
			"end_col": 9
		},
		{
			"id": 468,
			"tex": "114,009",
			"content": [
				"114,009"
			],
			"start_row": 47,
			"end_row": 47,
			"start_col": 4,
			"end_col": 4
		},
		{
			"id": 324,
			"tex": "MANN-a27",
			"content": [
				"MANN-a27"
			],
			"start_row": 33,
			"end_row": 33,
			"start_col": 0,
			"end_col": 0
		},
		{
			"id": 469,
			"tex": "\\bf{3}",
			"content": [
				"3"
			],
			"start_row": 47,
			"end_row": 47,
			"start_col": 5,
			"end_col": 5
		},
		{
			"id": 325,
			"tex": "38,019",
			"content": [
				"38,019"
			],
			"start_row": 33,
			"end_row": 33,
			"start_col": 1,
			"end_col": 1
		},
		{
			"id": 470,
			"tex": "(36)",
			"content": [
				"(36)"
			],
			"start_row": 47,
			"end_row": 47,
			"start_col": 6,
			"end_col": 6
		},
		{
			"id": 326,
			"tex": "9",
			"content": [
				"9"
			],
			"start_row": 33,
			"end_row": 33,
			"start_col": 2,
			"end_col": 2
		},
		{
			"id": 471,
			"tex": "137,568",
			"content": [
				"137,568"
			],
			"start_row": 47,
			"end_row": 47,
			"start_col": 7,
			"end_col": 7
		},
		{
			"id": 327,
			"tex": "(126)",
			"content": [
				"(126)"
			],
			"start_row": 33,
			"end_row": 33,
			"start_col": 3,
			"end_col": 3
		},
		{
			"id": 472,
			"tex": "5",
			"content": [
				"5"
			],
			"start_row": 47,
			"end_row": 47,
			"start_col": 8,
			"end_col": 8
		},
		{
			"id": 329,
			"tex": "\\bf{6}",
			"content": [
				"6"
			],
			"start_row": 33,
			"end_row": 33,
			"start_col": 5,
			"end_col": 5
		},
		{
			"id": 473,
			"tex": "(36)",
			"content": [
				"(36)"
			],
			"start_row": 47,
			"end_row": 47,
			"start_col": 9,
			"end_col": 9
		},
		{
			"id": 330,
			"tex": "(126)",
			"content": [
				"(126)"
			],
			"start_row": 33,
			"end_row": 33,
			"start_col": 6,
			"end_col": 6
		},
		{
			"id": 474,
			"tex": "p-hat500-3",
			"content": [
				"p-hat500-3"
			],
			"start_row": 48,
			"end_row": 48,
			"start_col": 0,
			"end_col": 0
		},
		{
			"id": 331,
			"tex": "38,597",
			"content": [
				"38,597"
			],
			"start_row": 33,
			"end_row": 33,
			"start_col": 7,
			"end_col": 7
		},
		{
			"id": 475,
			"tex": "515,071,375",
			"content": [
				"515,071,375"
			],
			"start_row": 48,
			"end_row": 48,
			"start_col": 1,
			"end_col": 1
		},
		{
			"id": 332,
			"tex": "8",
			"content": [
				"8"
			],
			"start_row": 33,
			"end_row": 33,
			"start_col": 8,
			"end_col": 8
		},
		{
			"id": 476,
			"tex": "---",
			"content": [
				"\u2014"
			],
			"start_row": 48,
			"end_row": 48,
			"start_col": 2,
			"end_col": 2
		},
		{
			"id": 333,
			"tex": "(126)",
			"content": [
				"(126)"
			],
			"start_row": 33,
			"end_row": 33,
			"start_col": 9,
			"end_col": 9
		},
		{
			"id": 477,
			"tex": "(47)",
			"content": [
				"(47)"
			],
			"start_row": 48,
			"end_row": 48,
			"start_col": 3,
			"end_col": 3
		},
		{
			"id": 334,
			"tex": "MANN-a45",
			"content": [
				"MANN-a45"
			],
			"start_row": 34,
			"end_row": 34,
			"start_col": 0,
			"end_col": 0
		},
		{
			"id": 478,
			"tex": "39,260,458",
			"content": [
				"39,260,458"
			],
			"start_row": 48,
			"end_row": 48,
			"start_col": 4,
			"end_col": 4
		},
		{
			"id": 335,
			"tex": "2,851,572",
			"content": [
				"2,851,572"
			],
			"start_row": 34,
			"end_row": 34,
			"start_col": 1,
			"end_col": 1
		},
		{
			"id": 479,
			"tex": "\\bf{1,381}",
			"content": [
				"1,381"
			],
			"start_row": 48,
			"end_row": 48,
			"start_col": 5,
			"end_col": 5
		},
		{
			"id": 336,
			"tex": "4,989",
			"content": [
				"4,989"
			],
			"start_row": 34,
			"end_row": 34,
			"start_col": 2,
			"end_col": 2
		},
		{
			"id": 480,
			"tex": "(50)",
			"content": [
				"(50)"
			],
			"start_row": 48,
			"end_row": 48,
			"start_col": 6,
			"end_col": 6
		},
		{
			"id": 337,
			"tex": "(345)",
			"content": [
				"(345)"
			],
			"start_row": 34,
			"end_row": 34,
			"start_col": 3,
			"end_col": 3
		},
		{
			"id": 481,
			"tex": "104,684,054",
			"content": [
				"104,684,054"
			],
			"start_row": 48,
			"end_row": 48,
			"start_col": 7,
			"end_col": 7
		},
		{
			"id": 338,
			"tex": "2,851,572",
			"content": [
				"2,851,572"
			],
			"start_row": 34,
			"end_row": 34,
			"start_col": 4,
			"end_col": 4
		},
		{
			"id": 482,
			"tex": "4,945",
			"content": [
				"4,945"
			],
			"start_row": 48,
			"end_row": 48,
			"start_col": 8,
			"end_col": 8
		},
		{
			"id": 339,
			"tex": "\\bf{3,766}",
			"content": [
				"3,766"
			],
			"start_row": 34,
			"end_row": 34,
			"start_col": 5,
			"end_col": 5
		},
		{
			"id": 483,
			"tex": "(50)",
			"content": [
				"(50)"
			],
			"start_row": 48,
			"end_row": 48,
			"start_col": 9,
			"end_col": 9
		},
		{
			"id": 340,
			"tex": "(345)",
			"content": [
				"(345)"
			],
			"start_row": 34,
			"end_row": 34,
			"start_col": 6,
			"end_col": 6
		},
		{
			"id": 484,
			"tex": "p-hat700-1",
			"content": [
				"p-hat700-1"
			],
			"start_row": 49,
			"end_row": 49,
			"start_col": 0,
			"end_col": 0
		},
		{
			"id": 341,
			"tex": "2,545,131",
			"content": [
				"2,545,131"
			],
			"start_row": 34,
			"end_row": 34,
			"start_col": 7,
			"end_col": 7
		},
		{
			"id": 485,
			"tex": "36,925",
			"content": [
				"36,925"
			],
			"start_row": 49,
			"end_row": 49,
			"start_col": 1,
			"end_col": 1
		},
		{
			"id": 342,
			"tex": "4,118",
			"content": [
				"4,118"
			],
			"start_row": 34,
			"end_row": 34,
			"start_col": 8,
			"end_col": 8
		},
		{
			"id": 486,
			"tex": "0",
			"content": [
				"0"
			],
			"start_row": 49,
			"end_row": 49,
			"start_col": 2,
			"end_col": 2
		},
		{
			"id": 343,
			"tex": "(345)",
			"content": [
				"(345)"
			],
			"start_row": 34,
			"end_row": 34,
			"start_col": 9,
			"end_col": 9
		},
		{
			"id": 487,
			"tex": "(11)",
			"content": [
				"(11)"
			],
			"start_row": 49,
			"end_row": 49,
			"start_col": 3,
			"end_col": 3
		},
		{
			"id": 344,
			"tex": "MANN-a81",
			"content": [
				"MANN-a81"
			],
			"start_row": 35,
			"end_row": 35,
			"start_col": 0,
			"end_col": 0
		},
		{
			"id": 488,
			"tex": "26,649",
			"content": [
				"26,649"
			],
			"start_row": 49,
			"end_row": 49,
			"start_col": 4,
			"end_col": 4
		},
		{
			"id": 345,
			"tex": "550,869",
			"content": [
				"550,869"
			],
			"start_row": 35,
			"end_row": 35,
			"start_col": 1,
			"end_col": 1
		},
		{
			"id": 489,
			"tex": "0",
			"content": [
				"0"
			],
			"start_row": 49,
			"end_row": 49,
			"start_col": 5,
			"end_col": 5
		},
		{
			"id": 346,
			"tex": "---",
			"content": [
				"\u2014"
			],
			"start_row": 35,
			"end_row": 35,
			"start_col": 2,
			"end_col": 2
		},
		{
			"id": 490,
			"tex": "(11)",
			"content": [
				"(11)"
			],
			"start_row": 49,
			"end_row": 49,
			"start_col": 6,
			"end_col": 6
		},
		{
			"id": 347,
			"tex": "(1100)",
			"content": [
				"(1100)"
			],
			"start_row": 35,
			"end_row": 35,
			"start_col": 3,
			"end_col": 3
		},
		{
			"id": 491,
			"tex": "22,811",
			"content": [
				"22,811"
			],
			"start_row": 49,
			"end_row": 49,
			"start_col": 7,
			"end_col": 7
		},
		{
			"id": 348,
			"tex": "631,141",
			"content": [
				"631,141"
			],
			"start_row": 35,
			"end_row": 35,
			"start_col": 4,
			"end_col": 4
		},
		{
			"id": 492,
			"tex": "0",
			"content": [
				"0"
			],
			"start_row": 49,
			"end_row": 49,
			"start_col": 8,
			"end_col": 8
		},
		{
			"id": 349,
			"tex": "---",
			"content": [
				"\u2014"
			],
			"start_row": 35,
			"end_row": 35,
			"start_col": 5,
			"end_col": 5
		},
		{
			"id": 493,
			"tex": "(11)",
			"content": [
				"(11)"
			],
			"start_row": 49,
			"end_row": 49,
			"start_col": 9,
			"end_col": 9
		},
		{
			"id": 350,
			"tex": "(1100)",
			"content": [
				"(1100)"
			],
			"start_row": 35,
			"end_row": 35,
			"start_col": 6,
			"end_col": 6
		},
		{
			"id": 494,
			"tex": "p-hat700-2",
			"content": [
				"p-hat700-2"
			],
			"start_row": 50,
			"end_row": 50,
			"start_col": 0,
			"end_col": 0
		},
		{
			"id": 351,
			"tex": "551,612",
			"content": [
				"551,612"
			],
			"start_row": 35,
			"end_row": 35,
			"start_col": 7,
			"end_col": 7
		},
		{
			"id": 495,
			"tex": "18,968,155",
			"content": [
				"18,968,155"
			],
			"start_row": 50,
			"end_row": 50,
			"start_col": 1,
			"end_col": 1
		},
		{
			"id": 352,
			"tex": "---",
			"content": [
				"\u2014"
			],
			"start_row": 35,
			"end_row": 35,
			"start_col": 8,
			"end_col": 8
		},
		{
			"id": 496,
			"tex": "508",
			"content": [
				"508"
			],
			"start_row": 50,
			"end_row": 50,
			"start_col": 2,
			"end_col": 2
		},
		{
			"id": 353,
			"tex": "(1100)",
			"content": [
				"(1100)"
			],
			"start_row": 35,
			"end_row": 35,
			"start_col": 9,
			"end_col": 9
		},
		{
			"id": 497,
			"tex": "(44)",
			"content": [
				"(44)"
			],
			"start_row": 50,
			"end_row": 50,
			"start_col": 3,
			"end_col": 3
		},
		{
			"id": 354,
			"tex": "MANN-a9",
			"content": [
				"MANN-a9"
			],
			"start_row": 36,
			"end_row": 36,
			"start_col": 0,
			"end_col": 0
		},
		{
			"id": 498,
			"tex": "750,903",
			"content": [
				"750,903"
			],
			"start_row": 50,
			"end_row": 50,
			"start_col": 4,
			"end_col": 4
		},
		{
			"id": 355,
			"tex": "71",
			"content": [
				"71"
			],
			"start_row": 36,
			"end_row": 36,
			"start_col": 1,
			"end_col": 1
		},
		{
			"id": 499,
			"tex": "\\bf{27}",
			"content": [
				"27"
			],
			"start_row": 50,
			"end_row": 50,
			"start_col": 5,
			"end_col": 5
		},
		{
			"id": 356,
			"tex": "0",
			"content": [
				"0"
			],
			"start_row": 36,
			"end_row": 36,
			"start_col": 2,
			"end_col": 2
		},
		{
			"id": 500,
			"tex": "(44)",
			"content": [
				"(44)"
			],
			"start_row": 50,
			"end_row": 50,
			"start_col": 6,
			"end_col": 6
		},
		{
			"id": 357,
			"tex": "(16)",
			"content": [
				"(16)"
			],
			"start_row": 36,
			"end_row": 36,
			"start_col": 3,
			"end_col": 3
		},
		{
			"id": 501,
			"tex": "149,0522",
			"content": [
				"149,0522"
			],
			"start_row": 50,
			"end_row": 50,
			"start_col": 7,
			"end_col": 7
		},
		{
			"id": 358,
			"tex": "71",
			"content": [
				"71"
			],
			"start_row": 36,
			"end_row": 36,
			"start_col": 4,
			"end_col": 4
		},
		{
			"id": 502,
			"tex": "74",
			"content": [
				"74"
			],
			"start_row": 50,
			"end_row": 50,
			"start_col": 8,
			"end_col": 8
		},
		{
			"id": 359,
			"tex": "0",
			"content": [
				"0"
			],
			"start_row": 36,
			"end_row": 36,
			"start_col": 5,
			"end_col": 5
		},
		{
			"id": 503,
			"tex": "(44)",
			"content": [
				"(44)"
			],
			"start_row": 50,
			"end_row": 50,
			"start_col": 9,
			"end_col": 9
		},
		{
			"id": 360,
			"tex": "(16)",
			"content": [
				"(16)"
			],
			"start_row": 36,
			"end_row": 36,
			"start_col": 6,
			"end_col": 6
		},
		{
			"id": 504,
			"tex": "p-hat700-3",
			"content": [
				"p-hat700-3"
			],
			"start_row": 51,
			"end_row": 51,
			"start_col": 0,
			"end_col": 0
		},
		{
			"id": 361,
			"tex": "39",
			"content": [
				"39"
			],
			"start_row": 36,
			"end_row": 36,
			"start_col": 7,
			"end_col": 7
		},
		{
			"id": 505,
			"tex": "570,423,439",
			"content": [
				"570,423,439"
			],
			"start_row": 51,
			"end_row": 51,
			"start_col": 1,
			"end_col": 1
		},
		{
			"id": 362,
			"tex": "0",
			"content": [
				"0"
			],
			"start_row": 36,
			"end_row": 36,
			"start_col": 8,
			"end_col": 8
		},
		{
			"id": 506,
			"tex": "---",
			"content": [
				"\u2014"
			],
			"start_row": 51,
			"end_row": 51,
			"start_col": 2,
			"end_col": 2
		},
		{
			"id": 363,
			"tex": "(16)",
			"content": [
				"(16)"
			],
			"start_row": 36,
			"end_row": 36,
			"start_col": 9,
			"end_col": 9
		},
		{
			"id": 507,
			"tex": "(48)",
			"content": [
				"(48)"
			],
			"start_row": 51,
			"end_row": 51,
			"start_col": 3,
			"end_col": 3
		},
		{
			"id": 364,
			"tex": "p-hat1000-1",
			"content": [
				"p-hat1000-1"
			],
			"start_row": 37,
			"end_row": 37,
			"start_col": 0,
			"end_col": 0
		},
		{
			"id": 508,
			"tex": "255,745,746",
			"content": [
				"255,745,746"
			],
			"start_row": 51,
			"end_row": 51,
			"start_col": 4,
			"end_col": 4
		},
		{
			"id": 365,
			"tex": "237,437",
			"content": [
				"237,437"
			],
			"start_row": 37,
			"end_row": 37,
			"start_col": 1,
			"end_col": 1
		},
		{
			"id": 509,
			"tex": "---",
			"content": [
				"\u2014"
			],
			"start_row": 51,
			"end_row": 51,
			"start_col": 5,
			"end_col": 5
		},
		{
			"id": 366,
			"tex": "2",
			"content": [
				"2"
			],
			"start_row": 37,
			"end_row": 37,
			"start_col": 2,
			"end_col": 2
		},
		{
			"id": 510,
			"tex": "(62)",
			"content": [
				"(62)"
			],
			"start_row": 51,
			"end_row": 51,
			"start_col": 6,
			"end_col": 6
		},
		{
			"id": 367,
			"tex": "(10)",
			"content": [
				"(10)"
			],
			"start_row": 37,
			"end_row": 37,
			"start_col": 3,
			"end_col": 3
		},
		{
			"id": 511,
			"tex": "243,836,191",
			"content": [
				"243,836,191"
			],
			"start_row": 51,
			"end_row": 51,
			"start_col": 7,
			"end_col": 7
		},
		{
			"id": 368,
			"tex": "176,576",
			"content": [
				"176,576"
			],
			"start_row": 37,
			"end_row": 37,
			"start_col": 4,
			"end_col": 4
		},
		{
			"id": 512,
			"tex": "---",
			"content": [
				"\u2014"
			],
			"start_row": 51,
			"end_row": 51,
			"start_col": 8,
			"end_col": 8
		},
		{
			"id": 369,
			"tex": "2",
			"content": [
				"2"
			],
			"start_row": 37,
			"end_row": 37,
			"start_col": 5,
			"end_col": 5
		},
		{
			"id": 513,
			"tex": "(62)",
			"content": [
				"(62)"
			],
			"start_row": 51,
			"end_row": 51,
			"start_col": 9,
			"end_col": 9
		},
		{
			"id": 370,
			"tex": "(10)",
			"content": [
				"(10)"
			],
			"start_row": 37,
			"end_row": 37,
			"start_col": 6,
			"end_col": 6
		},
		{
			"id": 514,
			"tex": "san1000",
			"content": [
				"san1000"
			],
			"start_row": 52,
			"end_row": 52,
			"start_col": 0,
			"end_col": 0
		},
		{
			"id": 371,
			"tex": "151,033",
			"content": [
				"151,033"
			],
			"start_row": 37,
			"end_row": 37,
			"start_col": 7,
			"end_col": 7
		},
		{
			"id": 515,
			"tex": "302,895",
			"content": [
				"302,895"
			],
			"start_row": 52,
			"end_row": 52,
			"start_col": 1,
			"end_col": 1
		},
		{
			"id": 372,
			"tex": "2",
			"content": [
				"2"
			],
			"start_row": 37,
			"end_row": 37,
			"start_col": 8,
			"end_col": 8
		},
		{
			"id": 516,
			"tex": "20",
			"content": [
				"20"
			],
			"start_row": 52,
			"end_row": 52,
			"start_col": 2,
			"end_col": 2
		},
		{
			"id": 373,
			"tex": "(10)",
			"content": [
				"(10)"
			],
			"start_row": 37,
			"end_row": 37,
			"start_col": 9,
			"end_col": 9
		},
		{
			"id": 517,
			"tex": "(15)",
			"content": [
				"(15)"
			],
			"start_row": 52,
			"end_row": 52,
			"start_col": 3,
			"end_col": 3
		},
		{
			"id": 374,
			"tex": "p-hat1000-2",
			"content": [
				"p-hat1000-2"
			],
			"start_row": 38,
			"end_row": 38,
			"start_col": 0,
			"end_col": 0
		},
		{
			"id": 518,
			"tex": "150,725",
			"content": [
				"150,725"
			],
			"start_row": 52,
			"end_row": 52,
			"start_col": 4,
			"end_col": 4
		},
		{
			"id": 375,
			"tex": "466,616,845",
			"content": [
				"466,616,845"
			],
			"start_row": 38,
			"end_row": 38,
			"start_col": 1,
			"end_col": 1
		},
		{
			"id": 519,
			"tex": "10",
			"content": [
				"10"
			],
			"start_row": 52,
			"end_row": 52,
			"start_col": 5,
			"end_col": 5
		},
		{
			"id": 376,
			"tex": "---",
			"content": [
				"\u2014"
			],
			"start_row": 38,
			"end_row": 38,
			"start_col": 2,
			"end_col": 2
		},
		{
			"id": 520,
			"tex": "(15)",
			"content": [
				"(15)"
			],
			"start_row": 52,
			"end_row": 52,
			"start_col": 6,
			"end_col": 6
		},
		{
			"id": 377,
			"tex": "(45)",
			"content": [
				"(45)"
			],
			"start_row": 38,
			"end_row": 38,
			"start_col": 3,
			"end_col": 3
		},
		{
			"id": 521,
			"tex": "53,215",
			"content": [
				"53,215"
			],
			"start_row": 52,
			"end_row": 52,
			"start_col": 7,
			"end_col": 7
		},
		{
			"id": 378,
			"tex": "34,473,978",
			"content": [
				"34,473,978"
			],
			"start_row": 38,
			"end_row": 38,
			"start_col": 4,
			"end_col": 4
		},
		{
			"id": 522,
			"tex": "\\bf{3}",
			"content": [
				"3"
			],
			"start_row": 52,
			"end_row": 52,
			"start_col": 8,
			"end_col": 8
		},
		{
			"id": 379,
			"tex": "\\bf{1,401}",
			"content": [
				"1,401"
			],
			"start_row": 38,
			"end_row": 38,
			"start_col": 5,
			"end_col": 5
		},
		{
			"id": 523,
			"tex": "(15)",
			"content": [
				"(15)"
			],
			"start_row": 52,
			"end_row": 52,
			"start_col": 9,
			"end_col": 9
		},
		{
			"id": 380,
			"tex": "(46)",
			"content": [
				"(46)"
			],
			"start_row": 38,
			"end_row": 38,
			"start_col": 6,
			"end_col": 6
		},
		{
			"id": 524,
			"tex": "san200-0.7-1",
			"content": [
				"san200-0.7-1"
			],
			"start_row": 53,
			"end_row": 53,
			"start_col": 0,
			"end_col": 0
		},
		{
			"id": 381,
			"tex": "166,655,543",
			"content": [
				"166,655,543"
			],
			"start_row": 38,
			"end_row": 38,
			"start_col": 7,
			"end_col": 7
		},
		{
			"id": 525,
			"tex": "12,355",
			"content": [
				"12,355"
			],
			"start_row": 53,
			"end_row": 53,
			"start_col": 1,
			"end_col": 1
		},
		{
			"id": 382,
			"tex": "7,565",
			"content": [
				"7,565"
			],
			"start_row": 38,
			"end_row": 38,
			"start_col": 8,
			"end_col": 8
		},
		{
			"id": 526,
			"tex": "0",
			"content": [
				"0"
			],
			"start_row": 53,
			"end_row": 53,
			"start_col": 2,
			"end_col": 2
		},
		{
			"id": 383,
			"tex": "(46)",
			"content": [
				"(46)"
			],
			"start_row": 38,
			"end_row": 38,
			"start_col": 9,
			"end_col": 9
		},
		{
			"id": 527,
			"tex": "(30)",
			"content": [
				"(30)"
			],
			"start_row": 53,
			"end_row": 53,
			"start_col": 3,
			"end_col": 3
		},
		{
			"id": 384,
			"tex": "p-hat1000-3",
			"content": [
				"p-hat1000-3"
			],
			"start_row": 39,
			"end_row": 39,
			"start_col": 0,
			"end_col": 0
		},
		{
			"id": 528,
			"tex": "13,399",
			"content": [
				"13,399"
			],
			"start_row": 53,
			"end_row": 53,
			"start_col": 4,
			"end_col": 4
		},
		{
			"id": 385,
			"tex": "440,569,803",
			"content": [
				"440,569,803"
			],
			"start_row": 39,
			"end_row": 39,
			"start_col": 1,
			"end_col": 1
		},
		{
			"id": 529,
			"tex": "0",
			"content": [
				"0"
			],
			"start_row": 53,
			"end_row": 53,
			"start_col": 5,
			"end_col": 5
		},
		{
			"id": 386,
			"tex": "---",
			"content": [
				"\u2014"
			],
			"start_row": 39,
			"end_row": 39,
			"start_col": 2,
			"end_col": 2
		},
		{
			"id": 530,
			"tex": "(30)",
			"content": [
				"(30)"
			],
			"start_row": 53,
			"end_row": 53,
			"start_col": 6,
			"end_col": 6
		},
		{
			"id": 387,
			"tex": "(52)",
			"content": [
				"(52)"
			],
			"start_row": 39,
			"end_row": 39,
			"start_col": 3,
			"end_col": 3
		},
		{
			"id": 531,
			"tex": "232",
			"content": [
				"232"
			],
			"start_row": 53,
			"end_row": 53,
			"start_col": 7,
			"end_col": 7
		},
		{
			"id": 388,
			"tex": "345,925,712",
			"content": [
				"345,925,712"
			],
			"start_row": 39,
			"end_row": 39,
			"start_col": 4,
			"end_col": 4
		},
		{
			"id": 532,
			"tex": "0",
			"content": [
				"0"
			],
			"start_row": 53,
			"end_row": 53,
			"start_col": 8,
			"end_col": 8
		},
		{
			"id": 389,
			"tex": "---",
			"content": [
				"\u2014"
			],
			"start_row": 39,
			"end_row": 39,
			"start_col": 5,
			"end_col": 5
		},
		{
			"id": 533,
			"tex": "(30)",
			"content": [
				"(30)"
			],
			"start_row": 53,
			"end_row": 53,
			"start_col": 9,
			"end_col": 9
		},
		{
			"id": 390,
			"tex": "(55)",
			"content": [
				"(55)"
			],
			"start_row": 39,
			"end_row": 39,
			"start_col": 6,
			"end_col": 6
		},
		{
			"id": 534,
			"tex": "san200-0.7-2",
			"content": [
				"san200-0.7-2"
			],
			"start_row": 54,
			"end_row": 54,
			"start_col": 0,
			"end_col": 0
		},
		{
			"id": 391,
			"tex": "298,537,771",
			"content": [
				"298,537,771"
			],
			"start_row": 39,
			"end_row": 39,
			"start_col": 7,
			"end_col": 7
		},
		{
			"id": 535,
			"tex": "767",
			"content": [
				"767"
			],
			"start_row": 54,
			"end_row": 54,
			"start_col": 1,
			"end_col": 1
		},
		{
			"id": 392,
			"tex": "---",
			"content": [
				"\u2014"
			],
			"start_row": 39,
			"end_row": 39,
			"start_col": 8,
			"end_col": 8
		},
		{
			"id": 536,
			"tex": "0",
			"content": [
				"0"
			],
			"start_row": 54,
			"end_row": 54,
			"start_col": 2,
			"end_col": 2
		},
		{
			"id": 393,
			"tex": "\\bf{(56)}",
			"content": [
				"(56)"
			],
			"start_row": 39,
			"end_row": 39,
			"start_col": 9,
			"end_col": 9
		},
		{
			"id": 537,
			"tex": "(18)",
			"content": [
				"(18)"
			],
			"start_row": 54,
			"end_row": 54,
			"start_col": 3,
			"end_col": 3
		},
		{
			"id": 394,
			"tex": "p-hat1500-1",
			"content": [
				"p-hat1500-1"
			],
			"start_row": 40,
			"end_row": 40,
			"start_col": 0,
			"end_col": 0
		},
		{
			"id": 538,
			"tex": "464",
			"content": [
				"464"
			],
			"start_row": 54,
			"end_row": 54,
			"start_col": 4,
			"end_col": 4
		},
		{
			"id": 395,
			"tex": "1,642,981",
			"content": [
				"1,642,981"
			],
			"start_row": 40,
			"end_row": 40,
			"start_col": 1,
			"end_col": 1
		},
		{
			"id": 539,
			"tex": "0",
			"content": [
				"0"
			],
			"start_row": 54,
			"end_row": 54,
			"start_col": 5,
			"end_col": 5
		},
		{
			"id": 35,
			"tex": "80,828",
			"content": [
				"80,828"
			],
			"start_row": 4,
			"end_row": 4,
			"start_col": 1,
			"end_col": 1
		},
		{
			"id": 36,
			"tex": "0",
			"content": [
				"0"
			],
			"start_row": 4,
			"end_row": 4,
			"start_col": 2,
			"end_col": 2
		},
		{
			"id": 37,
			"tex": "(17)",
			"content": [
				"(17)"
			],
			"start_row": 4,
			"end_row": 4,
			"start_col": 3,
			"end_col": 3
		},
		{
			"id": 38,
			"tex": "58,730",
			"content": [
				"58,730"
			],
			"start_row": 4,
			"end_row": 4,
			"start_col": 4,
			"end_col": 4
		},
		{
			"id": 39,
			"tex": "0",
			"content": [
				"0"
			],
			"start_row": 4,
			"end_row": 4,
			"start_col": 5,
			"end_col": 5
		},
		{
			"id": 40,
			"tex": "(17)",
			"content": [
				"(17)"
			],
			"start_row": 4,
			"end_row": 4,
			"start_col": 6,
			"end_col": 6
		},
		{
			"id": 41,
			"tex": "41,355",
			"content": [
				"41,355"
			],
			"start_row": 4,
			"end_row": 4,
			"start_col": 7,
			"end_col": 7
		},
		{
			"id": 42,
			"tex": "0",
			"content": [
				"0"
			],
			"start_row": 4,
			"end_row": 4,
			"start_col": 8,
			"end_col": 8
		},
		{
			"id": 43,
			"tex": "(17)",
			"content": [
				"(17)"
			],
			"start_row": 4,
			"end_row": 4,
			"start_col": 9,
			"end_col": 9
		},
		{
			"id": 44,
			"tex": "brock400-1",
			"content": [
				"brock400-1"
			],
			"start_row": 5,
			"end_row": 5,
			"start_col": 0,
			"end_col": 0
		},
		{
			"id": 45,
			"tex": "342,473,950",
			"content": [
				"342,473,950"
			],
			"start_row": 5,
			"end_row": 5,
			"start_col": 1,
			"end_col": 1
		},
		{
			"id": 46,
			"tex": "4,471",
			"content": [
				"4,471"
			],
			"start_row": 5,
			"end_row": 5,
			"start_col": 2,
			"end_col": 2
		},
		{
			"id": 47,
			"tex": "(27)",
			"content": [
				"(27)"
			],
			"start_row": 5,
			"end_row": 5,
			"start_col": 3,
			"end_col": 3
		},
		{
			"id": 48,
			"tex": "198,359,829",
			"content": [
				"198,359,829"
			],
			"start_row": 5,
			"end_row": 5,
			"start_col": 4,
			"end_col": 4
		},
		{
			"id": 49,
			"tex": "2,888",
			"content": [
				"2,888"
			],
			"start_row": 5,
			"end_row": 5,
			"start_col": 5,
			"end_col": 5
		},
		{
			"id": 50,
			"tex": "(27)",
			"content": [
				"(27)"
			],
			"start_row": 5,
			"end_row": 5,
			"start_col": 6,
			"end_col": 6
		},
		{
			"id": 51,
			"tex": "142,253,319",
			"content": [
				"142,253,319"
			],
			"start_row": 5,
			"end_row": 5,
			"start_col": 7,
			"end_col": 7
		},
		{
			"id": 52,
			"tex": "\\bf{2,551}",
			"content": [
				"2,551"
			],
			"start_row": 5,
			"end_row": 5,
			"start_col": 8,
			"end_col": 8
		},
		{
			"id": 53,
			"tex": "(27)",
			"content": [
				"(27)"
			],
			"start_row": 5,
			"end_row": 5,
			"start_col": 9,
			"end_col": 9
		},
		{
			"id": 54,
			"tex": "brock400-2",
			"content": [
				"brock400-2"
			],
			"start_row": 6,
			"end_row": 6,
			"start_col": 0,
			"end_col": 0
		},
		{
			"id": 55,
			"tex": "224,839,070",
			"content": [
				"224,839,070"
			],
			"start_row": 6,
			"end_row": 6,
			"start_col": 1,
			"end_col": 1
		},
		{
			"id": 56,
			"tex": "2,923",
			"content": [
				"2,923"
			],
			"start_row": 6,
			"end_row": 6,
			"start_col": 2,
			"end_col": 2
		},
		{
			"id": 57,
			"tex": "(29)",
			"content": [
				"(29)"
			],
			"start_row": 6,
			"end_row": 6,
			"start_col": 3,
			"end_col": 3
		},
		{
			"id": 58,
			"tex": "145,597,994",
			"content": [
				"145,597,994"
			],
			"start_row": 6,
			"end_row": 6,
			"start_col": 4,
			"end_col": 4
		},
		{
			"id": 59,
			"tex": "2,089",
			"content": [
				"2,089"
			],
			"start_row": 6,
			"end_row": 6,
			"start_col": 5,
			"end_col": 5
		},
		{
			"id": 60,
			"tex": "(29)",
			"content": [
				"(29)"
			],
			"start_row": 6,
			"end_row": 6,
			"start_col": 6,
			"end_col": 6
		},
		{
			"id": 61,
			"tex": "61,327,056",
			"content": [
				"61,327,056"
			],
			"start_row": 6,
			"end_row": 6,
			"start_col": 7,
			"end_col": 7
		},
		{
			"id": 62,
			"tex": "\\bf{1,199}",
			"content": [
				"1,199"
			],
			"start_row": 6,
			"end_row": 6,
			"start_col": 8,
			"end_col": 8
		},
		{
			"id": 63,
			"tex": "(29)",
			"content": [
				"(29)"
			],
			"start_row": 6,
			"end_row": 6,
			"start_col": 9,
			"end_col": 9
		},
		{
			"id": 64,
			"tex": "brock400-3",
			"content": [
				"brock400-3"
			],
			"start_row": 7,
			"end_row": 7,
			"start_col": 0,
			"end_col": 0
		},
		{
			"id": 65,
			"tex": "194,403,055",
			"content": [
				"194,403,055"
			],
			"start_row": 7,
			"end_row": 7,
			"start_col": 1,
			"end_col": 1
		},
		{
			"id": 66,
			"tex": "2,322",
			"content": [
				"2,322"
			],
			"start_row": 7,
			"end_row": 7,
			"start_col": 2,
			"end_col": 2
		},
		{
			"id": 67,
			"tex": "(31)",
			"content": [
				"(31)"
			],
			"start_row": 7,
			"end_row": 7,
			"start_col": 3,
			"end_col": 3
		},
		{
			"id": 68,
			"tex": "120,230,513",
			"content": [
				"120,230,513"
			],
			"start_row": 7,
			"end_row": 7,
			"start_col": 4,
			"end_col": 4
		},
		{
			"id": 0,
			"tex": "instance",
			"content": [
				"instance"
			],
			"start_row": 0,
			"end_row": 0,
			"start_col": 0,
			"end_col": 0
		},
		{
			"id": 69,
			"tex": "1,616",
			"content": [
				"1,616"
			],
			"start_row": 7,
			"end_row": 7,
			"start_col": 5,
			"end_col": 5
		},
		{
			"id": 70,
			"tex": "(31)",
			"content": [
				"(31)"
			],
			"start_row": 7,
			"end_row": 7,
			"start_col": 6,
			"end_col": 6
		},
		{
			"id": 1,
			"tex": "MCQ1",
			"content": [
				"MCQ1"
			],
			"start_row": 0,
			"end_row": 0,
			"start_col": 1,
			"end_col": 3
		},
		{
			"id": 2,
			"tex": "MCSa1",
			"content": [
				"MCSa1"
			],
			"start_row": 0,
			"end_row": 0,
			"start_col": 4,
			"end_col": 6
		},
		{
			"id": 71,
			"tex": "70,263,846",
			"content": [
				"70,263,846"
			],
			"start_row": 7,
			"end_row": 7,
			"start_col": 7,
			"end_col": 7
		},
		{
			"id": 3,
			"tex": "MCSb1",
			"content": [
				"MCSb1"
			],
			"start_row": 0,
			"end_row": 0,
			"start_col": 7,
			"end_col": 9
		},
		{
			"id": 72,
			"tex": "\\bf{1,234}",
			"content": [
				"1,234"
			],
			"start_row": 7,
			"end_row": 7,
			"start_col": 8,
			"end_col": 8
		},
		{
			"id": 73,
			"tex": "(31)",
			"content": [
				"(31)"
			],
			"start_row": 7,
			"end_row": 7,
			"start_col": 9,
			"end_col": 9
		},
		{
			"id": 74,
			"tex": "brock400-4",
			"content": [
				"brock400-4"
			],
			"start_row": 8,
			"end_row": 8,
			"start_col": 0,
			"end_col": 0
		},
		{
			"id": 75,
			"tex": "82,056,086",
			"content": [
				"82,056,086"
			],
			"start_row": 8,
			"end_row": 8,
			"start_col": 1,
			"end_col": 1
		},
		{
			"id": 4,
			"tex": "brock200-1",
			"content": [
				"brock200-1"
			],
			"start_row": 1,
			"end_row": 1,
			"start_col": 0,
			"end_col": 0
		},
		{
			"id": 76,
			"tex": "1,117",
			"content": [
				"1,117"
			],
			"start_row": 8,
			"end_row": 8,
			"start_col": 2,
			"end_col": 2
		},
		{
			"id": 5,
			"tex": "868,213",
			"content": [
				"868,213"
			],
			"start_row": 1,
			"end_row": 1,
			"start_col": 1,
			"end_col": 1
		},
		{
			"id": 77,
			"tex": "(33)",
			"content": [
				"(33)"
			],
			"start_row": 8,
			"end_row": 8,
			"start_col": 3,
			"end_col": 3
		},
		{
			"id": 6,
			"tex": "7",
			"content": [
				"7"
			],
			"start_row": 1,
			"end_row": 1,
			"start_col": 2,
			"end_col": 2
		},
		{
			"id": 78,
			"tex": "54,440,888",
			"content": [
				"54,440,888"
			],
			"start_row": 8,
			"end_row": 8,
			"start_col": 4,
			"end_col": 4
		},
		{
			"id": 7,
			"tex": "(21)",
			"content": [
				"(21)"
			],
			"start_row": 1,
			"end_row": 1,
			"start_col": 3,
			"end_col": 3
		},
		{
			"id": 79,
			"tex": "\\bf{802}",
			"content": [
				"802"
			],
			"start_row": 8,
			"end_row": 8,
			"start_col": 5,
			"end_col": 5
		},
		{
			"id": 8,
			"tex": "524,723",
			"content": [
				"524,723"
			],
			"start_row": 1,
			"end_row": 1,
			"start_col": 4,
			"end_col": 4
		},
		{
			"id": 80,
			"tex": "(33)",
			"content": [
				"(33)"
			],
			"start_row": 8,
			"end_row": 8,
			"start_col": 6,
			"end_col": 6
		},
		{
			"id": 9,
			"tex": "4",
			"content": [
				"4"
			],
			"start_row": 1,
			"end_row": 1,
			"start_col": 5,
			"end_col": 5
		},
		{
			"id": 81,
			"tex": "68,252,352",
			"content": [
				"68,252,352"
			],
			"start_row": 8,
			"end_row": 8,
			"start_col": 7,
			"end_col": 7
		},
		{
			"id": 10,
			"tex": "(21)",
			"content": [
				"(21)"
			],
			"start_row": 1,
			"end_row": 1,
			"start_col": 6,
			"end_col": 6
		},
		{
			"id": 82,
			"tex": "1,209",
			"content": [
				"1,209"
			],
			"start_row": 8,
			"end_row": 8,
			"start_col": 8,
			"end_col": 8
		},
		{
			"id": 11,
			"tex": "245,146",
			"content": [
				"245,146"
			],
			"start_row": 1,
			"end_row": 1,
			"start_col": 7,
			"end_col": 7
		},
		{
			"id": 83,
			"tex": "(33)",
			"content": [
				"(33)"
			],
			"start_row": 8,
			"end_row": 8,
			"start_col": 9,
			"end_col": 9
		},
		{
			"id": 12,
			"tex": "\\bf{3}",
			"content": [
				"3"
			],
			"start_row": 1,
			"end_row": 1,
			"start_col": 8,
			"end_col": 8
		},
		{
			"id": 84,
			"tex": "brock800-1",
			"content": [
				"brock800-1"
			],
			"start_row": 9,
			"end_row": 9,
			"start_col": 0,
			"end_col": 0
		},
		{
			"id": 13,
			"tex": "(21)",
			"content": [
				"(21)"
			],
			"start_row": 1,
			"end_row": 1,
			"start_col": 9,
			"end_col": 9
		},
		{
			"id": 85,
			"tex": "1,247,519,247",
			"content": [
				"1,247,519,247"
			],
			"start_row": 9,
			"end_row": 9,
			"start_col": 1,
			"end_col": 1
		},
		{
			"id": 14,
			"tex": "brock200-2",
			"content": [
				"brock200-2"
			],
			"start_row": 2,
			"end_row": 2,
			"start_col": 0,
			"end_col": 0
		},
		{
			"id": 86,
			"tex": "---",
			"content": [
				"\u2014"
			],
			"start_row": 9,
			"end_row": 9,
			"start_col": 2,
			"end_col": 2
		},
		{
			"id": 15,
			"tex": "4,330",
			"content": [
				"4,330"
			],
			"start_row": 2,
			"end_row": 2,
			"start_col": 1,
			"end_col": 1
		},
		{
			"id": 87,
			"tex": "\\bf{(23)}",
			"content": [
				"(23)"
			],
			"start_row": 9,
			"end_row": 9,
			"start_col": 3,
			"end_col": 3
		},
		{
			"id": 16,
			"tex": "0",
			"content": [
				"0"
			],
			"start_row": 2,
			"end_row": 2,
			"start_col": 2,
			"end_col": 2
		},
		{
			"id": 88,
			"tex": "1,055,945,239",
			"content": [
				"1,055,945,239"
			],
			"start_row": 9,
			"end_row": 9,
			"start_col": 4,
			"end_col": 4
		},
		{
			"id": 17,
			"tex": "(12)",
			"content": [
				"(12)"
			],
			"start_row": 2,
			"end_row": 2,
			"start_col": 3,
			"end_col": 3
		},
		{
			"id": 89,
			"tex": "---",
			"content": [
				"\u2014"
			],
			"start_row": 9,
			"end_row": 9,
			"start_col": 5,
			"end_col": 5
		},
		{
			"id": 18,
			"tex": "3,826",
			"content": [
				"3,826"
			],
			"start_row": 2,
			"end_row": 2,
			"start_col": 4,
			"end_col": 4
		},
		{
			"id": 90,
			"tex": "\\bf{(23)}",
			"content": [
				"(23)"
			],
			"start_row": 9,
			"end_row": 9,
			"start_col": 6,
			"end_col": 6
		},
		{
			"id": 19,
			"tex": "0",
			"content": [
				"0"
			],
			"start_row": 2,
			"end_row": 2,
			"start_col": 5,
			"end_col": 5
		},
		{
			"id": 91,
			"tex": "911,465,283",
			"content": [
				"911,465,283"
			],
			"start_row": 9,
			"end_row": 9,
			"start_col": 7,
			"end_col": 7
		},
		{
			"id": 20,
			"tex": "(12)",
			"content": [
				"(12)"
			],
			"start_row": 2,
			"end_row": 2,
			"start_col": 6,
			"end_col": 6
		},
		{
			"id": 92,
			"tex": "---",
			"content": [
				"\u2014"
			],
			"start_row": 9,
			"end_row": 9,
			"start_col": 8,
			"end_col": 8
		},
		{
			"id": 21,
			"tex": "3,229",
			"content": [
				"3,229"
			],
			"start_row": 2,
			"end_row": 2,
			"start_col": 7,
			"end_col": 7
		},
		{
			"id": 93,
			"tex": "(21)",
			"content": [
				"(21)"
			],
			"start_row": 9,
			"end_row": 9,
			"start_col": 9,
			"end_col": 9
		},
		{
			"id": 22,
			"tex": "0",
			"content": [
				"0"
			],
			"start_row": 2,
			"end_row": 2,
			"start_col": 8,
			"end_col": 8
		},
		{
			"id": 94,
			"tex": "brock800-2",
			"content": [
				"brock800-2"
			],
			"start_row": 10,
			"end_row": 10,
			"start_col": 0,
			"end_col": 0
		},
		{
			"id": 23,
			"tex": "(12)",
			"content": [
				"(12)"
			],
			"start_row": 2,
			"end_row": 2,
			"start_col": 9,
			"end_col": 9
		},
		{
			"id": 95,
			"tex": "1,387,973,191",
			"content": [
				"1,387,973,191"
			],
			"start_row": 10,
			"end_row": 10,
			"start_col": 1,
			"end_col": 1
		},
		{
			"id": 24,
			"tex": "brock200-3",
			"content": [
				"brock200-3"
			],
			"start_row": 3,
			"end_row": 3,
			"start_col": 0,
			"end_col": 0
		},
		{
			"id": 96,
			"tex": "---",
			"content": [
				"\u2014"
			],
			"start_row": 10,
			"end_row": 10,
			"start_col": 2,
			"end_col": 2
		},
		{
			"id": 25,
			"tex": "17,817",
			"content": [
				"17,817"
			],
			"start_row": 3,
			"end_row": 3,
			"start_col": 1,
			"end_col": 1
		},
		{
			"id": 97,
			"tex": "(21)",
			"content": [
				"(21)"
			],
			"start_row": 10,
			"end_row": 10,
			"start_col": 3,
			"end_col": 3
		},
		{
			"id": 26,
			"tex": "0",
			"content": [
				"0"
			],
			"start_row": 3,
			"end_row": 3,
			"start_col": 2,
			"end_col": 2
		},
		{
			"id": 98,
			"tex": "1,171,057,646",
			"content": [
				"1,171,057,646"
			],
			"start_row": 10,
			"end_row": 10,
			"start_col": 4,
			"end_col": 4
		},
		{
			"id": 27,
			"tex": "(15)",
			"content": [
				"(15)"
			],
			"start_row": 3,
			"end_row": 3,
			"start_col": 3,
			"end_col": 3
		},
		{
			"id": 99,
			"tex": "---",
			"content": [
				"\u2014"
			],
			"start_row": 10,
			"end_row": 10,
			"start_col": 5,
			"end_col": 5
		},
		{
			"id": 28,
			"tex": "14,565",
			"content": [
				"14,565"
			],
			"start_row": 3,
			"end_row": 3,
			"start_col": 4,
			"end_col": 4
		},
		{
			"id": 100,
			"tex": "\\bf{(24)}",
			"content": [
				"(24)"
			],
			"start_row": 10,
			"end_row": 10,
			"start_col": 6,
			"end_col": 6
		},
		{
			"id": 29,
			"tex": "0",
			"content": [
				"0"
			],
			"start_row": 3,
			"end_row": 3,
			"start_col": 5,
			"end_col": 5
		},
		{
			"id": 101,
			"tex": "914,638,570",
			"content": [
				"914,638,570"
			],
			"start_row": 10,
			"end_row": 10,
			"start_col": 7,
			"end_col": 7
		},
		{
			"id": 30,
			"tex": "(15)",
			"content": [
				"(15)"
			],
			"start_row": 3,
			"end_row": 3,
			"start_col": 6,
			"end_col": 6
		},
		{
			"id": 102,
			"tex": "---",
			"content": [
				"\u2014"
			],
			"start_row": 10,
			"end_row": 10,
			"start_col": 8,
			"end_col": 8
		},
		{
			"id": 31,
			"tex": "11,234",
			"content": [
				"11,234"
			],
			"start_row": 3,
			"end_row": 3,
			"start_col": 7,
			"end_col": 7
		},
		{
			"id": 103,
			"tex": "(21)",
			"content": [
				"(21)"
			],
			"start_row": 10,
			"end_row": 10,
			"start_col": 9,
			"end_col": 9
		},
		{
			"id": 32,
			"tex": "0",
			"content": [
				"0"
			],
			"start_row": 3,
			"end_row": 3,
			"start_col": 8,
			"end_col": 8
		},
		{
			"id": 104,
			"tex": "brock800-3",
			"content": [
				"brock800-3"
			],
			"start_row": 11,
			"end_row": 11,
			"start_col": 0,
			"end_col": 0
		},
		{
			"id": 33,
			"tex": "(15)",
			"content": [
				"(15)"
			],
			"start_row": 3,
			"end_row": 3,
			"start_col": 9,
			"end_col": 9
		},
		{
			"id": 105,
			"tex": "1,332,309,827",
			"content": [
				"1,332,309,827"
			],
			"start_row": 11,
			"end_row": 11,
			"start_col": 1,
			"end_col": 1
		},
		{
			"id": 34,
			"tex": "brock200-4",
			"content": [
				"brock200-4"
			],
			"start_row": 4,
			"end_row": 4,
			"start_col": 0,
			"end_col": 0
		},
		{
			"id": 106,
			"tex": "---",
			"content": [
				"\u2014"
			],
			"start_row": 11,
			"end_row": 11,
			"start_col": 2,
			"end_col": 2
		},
		{
			"id": 179,
			"tex": "0",
			"content": [
				"0"
			],
			"start_row": 18,
			"end_row": 18,
			"start_col": 5,
			"end_col": 5
		},
		{
			"id": 180,
			"tex": "(26)",
			"content": [
				"(26)"
			],
			"start_row": 18,
			"end_row": 18,
			"start_col": 6,
			"end_col": 6
		},
		{
			"id": 181,
			"tex": "26",
			"content": [
				"26"
			],
			"start_row": 18,
			"end_row": 18,
			"start_col": 7,
			"end_col": 7
		},
		{
			"id": 182,
			"tex": "0",
			"content": [
				"0"
			],
			"start_row": 18,
			"end_row": 18,
			"start_col": 8,
			"end_col": 8
		},
		{
			"id": 183,
			"tex": "(26)",
			"content": [
				"(26)"
			],
			"start_row": 18,
			"end_row": 18,
			"start_col": 9,
			"end_col": 9
		},
		{
			"id": 184,
			"tex": "c-fat500-5",
			"content": [
				"c-fat500-5"
			],
			"start_row": 19,
			"end_row": 19,
			"start_col": 0,
			"end_col": 0
		},
		{
			"id": 185,
			"tex": "64",
			"content": [
				"64"
			],
			"start_row": 19,
			"end_row": 19,
			"start_col": 1,
			"end_col": 1
		},
		{
			"id": 186,
			"tex": "0",
			"content": [
				"0"
			],
			"start_row": 19,
			"end_row": 19,
			"start_col": 2,
			"end_col": 2
		},
		{
			"id": 187,
			"tex": "(64)",
			"content": [
				"(64)"
			],
			"start_row": 19,
			"end_row": 19,
			"start_col": 3,
			"end_col": 3
		},
		{
			"id": 188,
			"tex": "64",
			"content": [
				"64"
			],
			"start_row": 19,
			"end_row": 19,
			"start_col": 4,
			"end_col": 4
		},
		{
			"id": 189,
			"tex": "0",
			"content": [
				"0"
			],
			"start_row": 19,
			"end_row": 19,
			"start_col": 5,
			"end_col": 5
		},
		{
			"id": 190,
			"tex": "(64)",
			"content": [
				"(64)"
			],
			"start_row": 19,
			"end_row": 19,
			"start_col": 6,
			"end_col": 6
		},
		{
			"id": 191,
			"tex": "64",
			"content": [
				"64"
			],
			"start_row": 19,
			"end_row": 19,
			"start_col": 7,
			"end_col": 7
		},
		{
			"id": 192,
			"tex": "0",
			"content": [
				"0"
			],
			"start_row": 19,
			"end_row": 19,
			"start_col": 8,
			"end_col": 8
		},
		{
			"id": 193,
			"tex": "(64)",
			"content": [
				"(64)"
			],
			"start_row": 19,
			"end_row": 19,
			"start_col": 9,
			"end_col": 9
		},
		{
			"id": 194,
			"tex": "hamming10-2",
			"content": [
				"hamming10-2"
			],
			"start_row": 20,
			"end_row": 20,
			"start_col": 0,
			"end_col": 0
		},
		{
			"id": 195,
			"tex": "512",
			"content": [
				"512"
			],
			"start_row": 20,
			"end_row": 20,
			"start_col": 1,
			"end_col": 1
		},
		{
			"id": 196,
			"tex": "\\bf{0}",
			"content": [
				"0"
			],
			"start_row": 20,
			"end_row": 20,
			"start_col": 2,
			"end_col": 2
		},
		{
			"id": 197,
			"tex": "(512)",
			"content": [
				"(512)"
			],
			"start_row": 20,
			"end_row": 20,
			"start_col": 3,
			"end_col": 3
		},
		{
			"id": 198,
			"tex": "512",
			"content": [
				"512"
			],
			"start_row": 20,
			"end_row": 20,
			"start_col": 4,
			"end_col": 4
		},
		{
			"id": 199,
			"tex": "\\bf{0}",
			"content": [
				"0"
			],
			"start_row": 20,
			"end_row": 20,
			"start_col": 5,
			"end_col": 5
		},
		{
			"id": 200,
			"tex": "(512)",
			"content": [
				"(512)"
			],
			"start_row": 20,
			"end_row": 20,
			"start_col": 6,
			"end_col": 6
		},
		{
			"id": 201,
			"tex": "512",
			"content": [
				"512"
			],
			"start_row": 20,
			"end_row": 20,
			"start_col": 7,
			"end_col": 7
		},
		{
			"id": 202,
			"tex": "8",
			"content": [
				"8"
			],
			"start_row": 20,
			"end_row": 20,
			"start_col": 8,
			"end_col": 8
		},
		{
			"id": 203,
			"tex": "(512)",
			"content": [
				"(512)"
			],
			"start_row": 20,
			"end_row": 20,
			"start_col": 9,
			"end_col": 9
		},
		{
			"id": 204,
			"tex": "hamming10-4",
			"content": [
				"hamming10-4"
			],
			"start_row": 21,
			"end_row": 21,
			"start_col": 0,
			"end_col": 0
		},
		{
			"id": 205,
			"tex": "636,203,658",
			"content": [
				"636,203,658"
			],
			"start_row": 21,
			"end_row": 21,
			"start_col": 1,
			"end_col": 1
		},
		{
			"id": 206,
			"tex": "---",
			"content": [
				"\u2014"
			],
			"start_row": 21,
			"end_row": 21,
			"start_col": 2,
			"end_col": 2
		},
		{
			"id": 207,
			"tex": "\\bf{(40)}",
			"content": [
				"(40)"
			],
			"start_row": 21,
			"end_row": 21,
			"start_col": 3,
			"end_col": 3
		},
		{
			"id": 208,
			"tex": "950,939,457",
			"content": [
				"950,939,457"
			],
			"start_row": 21,
			"end_row": 21,
			"start_col": 4,
			"end_col": 4
		},
		{
			"id": 209,
			"tex": "---",
			"content": [
				"\u2014"
			],
			"start_row": 21,
			"end_row": 21,
			"start_col": 5,
			"end_col": 5
		},
		{
			"id": 210,
			"tex": "(37)",
			"content": [
				"(37)"
			],
			"start_row": 21,
			"end_row": 21,
			"start_col": 6,
			"end_col": 6
		},
		{
			"id": 211,
			"tex": "858,347,653",
			"content": [
				"858,347,653"
			],
			"start_row": 21,
			"end_row": 21,
			"start_col": 7,
			"end_col": 7
		},
		{
			"id": 212,
			"tex": "---",
			"content": [
				"\u2014"
			],
			"start_row": 21,
			"end_row": 21,
			"start_col": 8,
			"end_col": 8
		},
		{
			"id": 213,
			"tex": "(37)",
			"content": [
				"(37)"
			],
			"start_row": 21,
			"end_row": 21,
			"start_col": 9,
			"end_col": 9
		},
		{
			"id": 214,
			"tex": "hamming6-2",
			"content": [
				"hamming6-2"
			],
			"start_row": 22,
			"end_row": 22,
			"start_col": 0,
			"end_col": 0
		},
		{
			"id": 215,
			"tex": "32",
			"content": [
				"32"
			],
			"start_row": 22,
			"end_row": 22,
			"start_col": 1,
			"end_col": 1
		},
		{
			"id": 216,
			"tex": "0",
			"content": [
				"0"
			],
			"start_row": 22,
			"end_row": 22,
			"start_col": 2,
			"end_col": 2
		},
		{
			"id": 217,
			"tex": "(32)",
			"content": [
				"(32)"
			],
			"start_row": 22,
			"end_row": 22,
			"start_col": 3,
			"end_col": 3
		},
		{
			"id": 218,
			"tex": "32",
			"content": [
				"32"
			],
			"start_row": 22,
			"end_row": 22,
			"start_col": 4,
			"end_col": 4
		},
		{
			"id": 219,
			"tex": "0",
			"content": [
				"0"
			],
			"start_row": 22,
			"end_row": 22,
			"start_col": 5,
			"end_col": 5
		},
		{
			"id": 220,
			"tex": "(32)",
			"content": [
				"(32)"
			],
			"start_row": 22,
			"end_row": 22,
			"start_col": 6,
			"end_col": 6
		},
		{
			"id": 221,
			"tex": "32",
			"content": [
				"32"
			],
			"start_row": 22,
			"end_row": 22,
			"start_col": 7,
			"end_col": 7
		},
		{
			"id": 222,
			"tex": "0",
			"content": [
				"0"
			],
			"start_row": 22,
			"end_row": 22,
			"start_col": 8,
			"end_col": 8
		},
		{
			"id": 223,
			"tex": "(32)",
			"content": [
				"(32)"
			],
			"start_row": 22,
			"end_row": 22,
			"start_col": 9,
			"end_col": 9
		},
		{
			"id": 224,
			"tex": "hamming6-4",
			"content": [
				"hamming6-4"
			],
			"start_row": 23,
			"end_row": 23,
			"start_col": 0,
			"end_col": 0
		},
		{
			"id": 225,
			"tex": "82",
			"content": [
				"82"
			],
			"start_row": 23,
			"end_row": 23,
			"start_col": 1,
			"end_col": 1
		},
		{
			"id": 226,
			"tex": "0",
			"content": [
				"0"
			],
			"start_row": 23,
			"end_row": 23,
			"start_col": 2,
			"end_col": 2
		},
		{
			"id": 227,
			"tex": "(4)",
			"content": [
				"(4)"
			],
			"start_row": 23,
			"end_row": 23,
			"start_col": 3,
			"end_col": 3
		},
		{
			"id": 228,
			"tex": "82",
			"content": [
				"82"
			],
			"start_row": 23,
			"end_row": 23,
			"start_col": 4,
			"end_col": 4
		},
		{
			"id": 229,
			"tex": "0",
			"content": [
				"0"
			],
			"start_row": 23,
			"end_row": 23,
			"start_col": 5,
			"end_col": 5
		},
		{
			"id": 230,
			"tex": "(4)",
			"content": [
				"(4)"
			],
			"start_row": 23,
			"end_row": 23,
			"start_col": 6,
			"end_col": 6
		},
		{
			"id": 231,
			"tex": "82",
			"content": [
				"82"
			],
			"start_row": 23,
			"end_row": 23,
			"start_col": 7,
			"end_col": 7
		},
		{
			"id": 232,
			"tex": "0",
			"content": [
				"0"
			],
			"start_row": 23,
			"end_row": 23,
			"start_col": 8,
			"end_col": 8
		},
		{
			"id": 233,
			"tex": "(4)",
			"content": [
				"(4)"
			],
			"start_row": 23,
			"end_row": 23,
			"start_col": 9,
			"end_col": 9
		},
		{
			"id": 234,
			"tex": "hamming8-2",
			"content": [
				"hamming8-2"
			],
			"start_row": 24,
			"end_row": 24,
			"start_col": 0,
			"end_col": 0
		},
		{
			"id": 235,
			"tex": "128",
			"content": [
				"128"
			],
			"start_row": 24,
			"end_row": 24,
			"start_col": 1,
			"end_col": 1
		},
		{
			"id": 236,
			"tex": "0",
			"content": [
				"0"
			],
			"start_row": 24,
			"end_row": 24,
			"start_col": 2,
			"end_col": 2
		},
		{
			"id": 237,
			"tex": "(128)",
			"content": [
				"(128)"
			],
			"start_row": 24,
			"end_row": 24,
			"start_col": 3,
			"end_col": 3
		},
		{
			"id": 238,
			"tex": "128",
			"content": [
				"128"
			],
			"start_row": 24,
			"end_row": 24,
			"start_col": 4,
			"end_col": 4
		},
		{
			"id": 239,
			"tex": "0",
			"content": [
				"0"
			],
			"start_row": 24,
			"end_row": 24,
			"start_col": 5,
			"end_col": 5
		},
		{
			"id": 240,
			"tex": "(128)",
			"content": [
				"(128)"
			],
			"start_row": 24,
			"end_row": 24,
			"start_col": 6,
			"end_col": 6
		},
		{
			"id": 241,
			"tex": "128",
			"content": [
				"128"
			],
			"start_row": 24,
			"end_row": 24,
			"start_col": 7,
			"end_col": 7
		},
		{
			"id": 242,
			"tex": "0",
			"content": [
				"0"
			],
			"start_row": 24,
			"end_row": 24,
			"start_col": 8,
			"end_col": 8
		},
		{
			"id": 243,
			"tex": "(128)",
			"content": [
				"(128)"
			],
			"start_row": 24,
			"end_row": 24,
			"start_col": 9,
			"end_col": 9
		},
		{
			"id": 244,
			"tex": "hamming8-4",
			"content": [
				"hamming8-4"
			],
			"start_row": 25,
			"end_row": 25,
			"start_col": 0,
			"end_col": 0
		},
		{
			"id": 245,
			"tex": "41,492",
			"content": [
				"41,492"
			],
			"start_row": 25,
			"end_row": 25,
			"start_col": 1,
			"end_col": 1
		},
		{
			"id": 246,
			"tex": "0",
			"content": [
				"0"
			],
			"start_row": 25,
			"end_row": 25,
			"start_col": 2,
			"end_col": 2
		},
		{
			"id": 247,
			"tex": "(16)",
			"content": [
				"(16)"
			],
			"start_row": 25,
			"end_row": 25,
			"start_col": 3,
			"end_col": 3
		},
		{
			"id": 248,
			"tex": "36,452",
			"content": [
				"36,452"
			],
			"start_row": 25,
			"end_row": 25,
			"start_col": 4,
			"end_col": 4
		},
		{
			"id": 249,
			"tex": "0",
			"content": [
				"0"
			],
			"start_row": 25,
			"end_row": 25,
			"start_col": 5,
			"end_col": 5
		},
		{
			"id": 250,
			"tex": "(16)",
			"content": [
				"(16)"
			],
			"start_row": 25,
			"end_row": 25,
			"start_col": 6,
			"end_col": 6
		},
		{
			"id": 107,
			"tex": "(21)",
			"content": [
				"(21)"
			],
			"start_row": 11,
			"end_row": 11,
			"start_col": 3,
			"end_col": 3
		},
		{
			"id": 396,
			"tex": "16",
			"content": [
				"16"
			],
			"start_row": 40,
			"end_row": 40,
			"start_col": 2,
			"end_col": 2
		},
		{
			"id": 108,
			"tex": "1,159,165,900",
			"content": [
				"1,159,165,900"
			],
			"start_row": 11,
			"end_row": 11,
			"start_col": 4,
			"end_col": 4
		},
		{
			"id": 397,
			"tex": "(12)",
			"content": [
				"(12)"
			],
			"start_row": 40,
			"end_row": 40,
			"start_col": 3,
			"end_col": 3
		},
		{
			"id": 109,
			"tex": "---",
			"content": [
				"\u2014"
			],
			"start_row": 11,
			"end_row": 11,
			"start_col": 5,
			"end_col": 5
		},
		{
			"id": 398,
			"tex": "1,184,526",
			"content": [
				"1,184,526"
			],
			"start_row": 40,
			"end_row": 40,
			"start_col": 4,
			"end_col": 4
		},
		{
			"id": 110,
			"tex": "(21)",
			"content": [
				"(21)"
			],
			"start_row": 11,
			"end_row": 11,
			"start_col": 6,
			"end_col": 6
		},
		{
			"id": 399,
			"tex": "14",
			"content": [
				"14"
			],
			"start_row": 40,
			"end_row": 40,
			"start_col": 5,
			"end_col": 5
		},
		{
			"id": 111,
			"tex": "914,235,793",
			"content": [
				"914,235,793"
			],
			"start_row": 11,
			"end_row": 11,
			"start_col": 7,
			"end_col": 7
		},
		{
			"id": 400,
			"tex": "(12)",
			"content": [
				"(12)"
			],
			"start_row": 40,
			"end_row": 40,
			"start_col": 6,
			"end_col": 6
		},
		{
			"id": 112,
			"tex": "---",
			"content": [
				"\u2014"
			],
			"start_row": 11,
			"end_row": 11,
			"start_col": 8,
			"end_col": 8
		},
		{
			"id": 401,
			"tex": "990,246",
			"content": [
				"990,246"
			],
			"start_row": 40,
			"end_row": 40,
			"start_col": 7,
			"end_col": 7
		},
		{
			"id": 113,
			"tex": "(21)",
			"content": [
				"(21)"
			],
			"start_row": 11,
			"end_row": 11,
			"start_col": 9,
			"end_col": 9
		},
		{
			"id": 402,
			"tex": "14",
			"content": [
				"14"
			],
			"start_row": 40,
			"end_row": 40,
			"start_col": 8,
			"end_col": 8
		},
		{
			"id": 114,
			"tex": "brock800-4",
			"content": [
				"brock800-4"
			],
			"start_row": 12,
			"end_row": 12,
			"start_col": 0,
			"end_col": 0
		},
		{
			"id": 403,
			"tex": "(12)",
			"content": [
				"(12)"
			],
			"start_row": 40,
			"end_row": 40,
			"start_col": 9,
			"end_col": 9
		},
		{
			"id": 115,
			"tex": "804,901,115",
			"content": [
				"804,901,115"
			],
			"start_row": 12,
			"end_row": 12,
			"start_col": 1,
			"end_col": 1
		},
		{
			"id": 404,
			"tex": "p-hat1500-2",
			"content": [
				"p-hat1500-2"
			],
			"start_row": 41,
			"end_row": 41,
			"start_col": 0,
			"end_col": 0
		},
		{
			"id": 116,
			"tex": "---",
			"content": [
				"\u2014"
			],
			"start_row": 12,
			"end_row": 12,
			"start_col": 2,
			"end_col": 2
		},
		{
			"id": 405,
			"tex": "414,514,960",
			"content": [
				"414,514,960"
			],
			"start_row": 41,
			"end_row": 41,
			"start_col": 1,
			"end_col": 1
		},
		{
			"id": 117,
			"tex": "(26)",
			"content": [
				"(26)"
			],
			"start_row": 12,
			"end_row": 12,
			"start_col": 3,
			"end_col": 3
		},
		{
			"id": 406,
			"tex": "---",
			"content": [
				"\u2014"
			],
			"start_row": 41,
			"end_row": 41,
			"start_col": 2,
			"end_col": 2
		},
		{
			"id": 118,
			"tex": "640,444,536",
			"content": [
				"640,444,536"
			],
			"start_row": 12,
			"end_row": 12,
			"start_col": 4,
			"end_col": 4
		},
		{
			"id": 407,
			"tex": "(52)",
			"content": [
				"(52)"
			],
			"start_row": 41,
			"end_row": 41,
			"start_col": 3,
			"end_col": 3
		},
		{
			"id": 119,
			"tex": "\\bf{12,568}",
			"content": [
				"12,568"
			],
			"start_row": 12,
			"end_row": 12,
			"start_col": 5,
			"end_col": 5
		},
		{
			"id": 408,
			"tex": "231,498,292",
			"content": [
				"231,498,292"
			],
			"start_row": 41,
			"end_row": 41,
			"start_col": 4,
			"end_col": 4
		},
		{
			"id": 120,
			"tex": "(26)",
			"content": [
				"(26)"
			],
			"start_row": 12,
			"end_row": 12,
			"start_col": 6,
			"end_col": 6
		},
		{
			"id": 409,
			"tex": "---",
			"content": [
				"\u2014"
			],
			"start_row": 41,
			"end_row": 41,
			"start_col": 5,
			"end_col": 5
		},
		{
			"id": 121,
			"tex": "659,145,642",
			"content": [
				"659,145,642"
			],
			"start_row": 12,
			"end_row": 12,
			"start_col": 7,
			"end_col": 7
		},
		{
			"id": 410,
			"tex": "\\bf{(60)}",
			"content": [
				"(60)"
			],
			"start_row": 41,
			"end_row": 41,
			"start_col": 6,
			"end_col": 6
		},
		{
			"id": 122,
			"tex": "13,924",
			"content": [
				"13,924"
			],
			"start_row": 12,
			"end_row": 12,
			"start_col": 8,
			"end_col": 8
		},
		{
			"id": 411,
			"tex": "259,771,137",
			"content": [
				"259,771,137"
			],
			"start_row": 41,
			"end_row": 41,
			"start_col": 7,
			"end_col": 7
		},
		{
			"id": 123,
			"tex": "(26)",
			"content": [
				"(26)"
			],
			"start_row": 12,
			"end_row": 12,
			"start_col": 9,
			"end_col": 9
		},
		{
			"id": 412,
			"tex": "---",
			"content": [
				"\u2014"
			],
			"start_row": 41,
			"end_row": 41,
			"start_col": 8,
			"end_col": 8
		},
		{
			"id": 124,
			"tex": "c-fat200-1",
			"content": [
				"c-fat200-1"
			],
			"start_row": 13,
			"end_row": 13,
			"start_col": 0,
			"end_col": 0
		},
		{
			"id": 413,
			"tex": "(57)",
			"content": [
				"(57)"
			],
			"start_row": 41,
			"end_row": 41,
			"start_col": 9,
			"end_col": 9
		},
		{
			"id": 125,
			"tex": "24",
			"content": [
				"24"
			],
			"start_row": 13,
			"end_row": 13,
			"start_col": 1,
			"end_col": 1
		},
		{
			"id": 414,
			"tex": "p-hat1500-3",
			"content": [
				"p-hat1500-3"
			],
			"start_row": 42,
			"end_row": 42,
			"start_col": 0,
			"end_col": 0
		},
		{
			"id": 126,
			"tex": "0",
			"content": [
				"0"
			],
			"start_row": 13,
			"end_row": 13,
			"start_col": 2,
			"end_col": 2
		},
		{
			"id": 415,
			"tex": "570,637,417",
			"content": [
				"570,637,417"
			],
			"start_row": 42,
			"end_row": 42,
			"start_col": 1,
			"end_col": 1
		},
		{
			"id": 127,
			"tex": "(12)",
			"content": [
				"(12)"
			],
			"start_row": 13,
			"end_row": 13,
			"start_col": 3,
			"end_col": 3
		},
		{
			"id": 416,
			"tex": "---",
			"content": [
				"\u2014"
			],
			"start_row": 42,
			"end_row": 42,
			"start_col": 2,
			"end_col": 2
		},
		{
			"id": 128,
			"tex": "24",
			"content": [
				"24"
			],
			"start_row": 13,
			"end_row": 13,
			"start_col": 4,
			"end_col": 4
		},
		{
			"id": 417,
			"tex": "(56)",
			"content": [
				"(56)"
			],
			"start_row": 42,
			"end_row": 42,
			"start_col": 3,
			"end_col": 3
		},
		{
			"id": 129,
			"tex": "0",
			"content": [
				"0"
			],
			"start_row": 13,
			"end_row": 13,
			"start_col": 5,
			"end_col": 5
		},
		{
			"id": 418,
			"tex": "220,823,126",
			"content": [
				"220,823,126"
			],
			"start_row": 42,
			"end_row": 42,
			"start_col": 4,
			"end_col": 4
		},
		{
			"id": 130,
			"tex": "(12)",
			"content": [
				"(12)"
			],
			"start_row": 13,
			"end_row": 13,
			"start_col": 6,
			"end_col": 6
		},
		{
			"id": 419,
			"tex": "---",
			"content": [
				"\u2014"
			],
			"start_row": 42,
			"end_row": 42,
			"start_col": 5,
			"end_col": 5
		},
		{
			"id": 131,
			"tex": "23",
			"content": [
				"23"
			],
			"start_row": 13,
			"end_row": 13,
			"start_col": 7,
			"end_col": 7
		},
		{
			"id": 420,
			"tex": "(69)",
			"content": [
				"(69)"
			],
			"start_row": 42,
			"end_row": 42,
			"start_col": 6,
			"end_col": 6
		},
		{
			"id": 132,
			"tex": "0",
			"content": [
				"0"
			],
			"start_row": 13,
			"end_row": 13,
			"start_col": 8,
			"end_col": 8
		},
		{
			"id": 421,
			"tex": "176,987,047",
			"content": [
				"176,987,047"
			],
			"start_row": 42,
			"end_row": 42,
			"start_col": 7,
			"end_col": 7
		},
		{
			"id": 133,
			"tex": "(12)",
			"content": [
				"(12)"
			],
			"start_row": 13,
			"end_row": 13,
			"start_col": 9,
			"end_col": 9
		},
		{
			"id": 422,
			"tex": "---",
			"content": [
				"\u2014"
			],
			"start_row": 42,
			"end_row": 42,
			"start_col": 8,
			"end_col": 8
		},
		{
			"id": 134,
			"tex": "c-fat200-2",
			"content": [
				"c-fat200-2"
			],
			"start_row": 14,
			"end_row": 14,
			"start_col": 0,
			"end_col": 0
		},
		{
			"id": 423,
			"tex": "(69)",
			"content": [
				"(69)"
			],
			"start_row": 42,
			"end_row": 42,
			"start_col": 9,
			"end_col": 9
		},
		{
			"id": 135,
			"tex": "24",
			"content": [
				"24"
			],
			"start_row": 14,
			"end_row": 14,
			"start_col": 1,
			"end_col": 1
		},
		{
			"id": 424,
			"tex": "p-hat300-1",
			"content": [
				"p-hat300-1"
			],
			"start_row": 43,
			"end_row": 43,
			"start_col": 0,
			"end_col": 0
		},
		{
			"id": 136,
			"tex": "0",
			"content": [
				"0"
			],
			"start_row": 14,
			"end_row": 14,
			"start_col": 2,
			"end_col": 2
		},
		{
			"id": 425,
			"tex": "1,727",
			"content": [
				"1,727"
			],
			"start_row": 43,
			"end_row": 43,
			"start_col": 1,
			"end_col": 1
		},
		{
			"id": 137,
			"tex": "(24)",
			"content": [
				"(24)"
			],
			"start_row": 14,
			"end_row": 14,
			"start_col": 3,
			"end_col": 3
		},
		{
			"id": 426,
			"tex": "0",
			"content": [
				"0"
			],
			"start_row": 43,
			"end_row": 43,
			"start_col": 2,
			"end_col": 2
		},
		{
			"id": 138,
			"tex": "24",
			"content": [
				"24"
			],
			"start_row": 14,
			"end_row": 14,
			"start_col": 4,
			"end_col": 4
		},
		{
			"id": 427,
			"tex": "(8)",
			"content": [
				"(8)"
			],
			"start_row": 43,
			"end_row": 43,
			"start_col": 3,
			"end_col": 3
		},
		{
			"id": 139,
			"tex": "0",
			"content": [
				"0"
			],
			"start_row": 14,
			"end_row": 14,
			"start_col": 5,
			"end_col": 5
		},
		{
			"id": 428,
			"tex": "1,480",
			"content": [
				"1,480"
			],
			"start_row": 43,
			"end_row": 43,
			"start_col": 4,
			"end_col": 4
		},
		{
			"id": 140,
			"tex": "(24)",
			"content": [
				"(24)"
			],
			"start_row": 14,
			"end_row": 14,
			"start_col": 6,
			"end_col": 6
		},
		{
			"id": 429,
			"tex": "0",
			"content": [
				"0"
			],
			"start_row": 43,
			"end_row": 43,
			"start_col": 5,
			"end_col": 5
		},
		{
			"id": 141,
			"tex": "24",
			"content": [
				"24"
			],
			"start_row": 14,
			"end_row": 14,
			"start_col": 7,
			"end_col": 7
		},
		{
			"id": 430,
			"tex": "(8)",
			"content": [
				"(8)"
			],
			"start_row": 43,
			"end_row": 43,
			"start_col": 6,
			"end_col": 6
		},
		{
			"id": 142,
			"tex": "0",
			"content": [
				"0"
			],
			"start_row": 14,
			"end_row": 14,
			"start_col": 8,
			"end_col": 8
		},
		{
			"id": 431,
			"tex": "1,305",
			"content": [
				"1,305"
			],
			"start_row": 43,
			"end_row": 43,
			"start_col": 7,
			"end_col": 7
		},
		{
			"id": 143,
			"tex": "(24)",
			"content": [
				"(24)"
			],
			"start_row": 14,
			"end_row": 14,
			"start_col": 9,
			"end_col": 9
		},
		{
			"id": 432,
			"tex": "0",
			"content": [
				"0"
			],
			"start_row": 43,
			"end_row": 43,
			"start_col": 8,
			"end_col": 8
		},
		{
			"id": 144,
			"tex": "c-fat200-5",
			"content": [
				"c-fat200-5"
			],
			"start_row": 15,
			"end_row": 15,
			"start_col": 0,
			"end_col": 0
		},
		{
			"id": 433,
			"tex": "(8)",
			"content": [
				"(8)"
			],
			"start_row": 43,
			"end_row": 43,
			"start_col": 9,
			"end_col": 9
		},
		{
			"id": 145,
			"tex": "139",
			"content": [
				"139"
			],
			"start_row": 15,
			"end_row": 15,
			"start_col": 1,
			"end_col": 1
		},
		{
			"id": 434,
			"tex": "p-hat300-2",
			"content": [
				"p-hat300-2"
			],
			"start_row": 44,
			"end_row": 44,
			"start_col": 0,
			"end_col": 0
		},
		{
			"id": 146,
			"tex": "0",
			"content": [
				"0"
			],
			"start_row": 15,
			"end_row": 15,
			"start_col": 2,
			"end_col": 2
		},
		{
			"id": 435,
			"tex": "13,814",
			"content": [
				"13,814"
			],
			"start_row": 44,
			"end_row": 44,
			"start_col": 1,
			"end_col": 1
		},
		{
			"id": 147,
			"tex": "(58)",
			"content": [
				"(58)"
			],
			"start_row": 15,
			"end_row": 15,
			"start_col": 3,
			"end_col": 3
		},
		{
			"id": 436,
			"tex": "0",
			"content": [
				"0"
			],
			"start_row": 44,
			"end_row": 44,
			"start_col": 2,
			"end_col": 2
		},
		{
			"id": 148,
			"tex": "139",
			"content": [
				"139"
			],
			"start_row": 15,
			"end_row": 15,
			"start_col": 4,
			"end_col": 4
		},
		{
			"id": 437,
			"tex": "(25)",
			"content": [
				"(25)"
			],
			"start_row": 44,
			"end_row": 44,
			"start_col": 3,
			"end_col": 3
		},
		{
			"id": 149,
			"tex": "0",
			"content": [
				"0"
			],
			"start_row": 15,
			"end_row": 15,
			"start_col": 5,
			"end_col": 5
		},
		{
			"id": 438,
			"tex": "4,256",
			"content": [
				"4,256"
			],
			"start_row": 44,
			"end_row": 44,
			"start_col": 4,
			"end_col": 4
		},
		{
			"id": 150,
			"tex": "(58)",
			"content": [
				"(58)"
			],
			"start_row": 15,
			"end_row": 15,
			"start_col": 6,
			"end_col": 6
		},
		{
			"id": 439,
			"tex": "0",
			"content": [
				"0"
			],
			"start_row": 44,
			"end_row": 44,
			"start_col": 5,
			"end_col": 5
		},
		{
			"id": 151,
			"tex": "139",
			"content": [
				"139"
			],
			"start_row": 15,
			"end_row": 15,
			"start_col": 7,
			"end_col": 7
		},
		{
			"id": 440,
			"tex": "(25)",
			"content": [
				"(25)"
			],
			"start_row": 44,
			"end_row": 44,
			"start_col": 6,
			"end_col": 6
		},
		{
			"id": 152,
			"tex": "0",
			"content": [
				"0"
			],
			"start_row": 15,
			"end_row": 15,
			"start_col": 8,
			"end_col": 8
		},
		{
			"id": 441,
			"tex": "4,877",
			"content": [
				"4,877"
			],
			"start_row": 44,
			"end_row": 44,
			"start_col": 7,
			"end_col": 7
		},
		{
			"id": 153,
			"tex": "(58)",
			"content": [
				"(58)"
			],
			"start_row": 15,
			"end_row": 15,
			"start_col": 9,
			"end_col": 9
		},
		{
			"id": 442,
			"tex": "0",
			"content": [
				"0"
			],
			"start_row": 44,
			"end_row": 44,
			"start_col": 8,
			"end_col": 8
		},
		{
			"id": 154,
			"tex": "c-fat500-10",
			"content": [
				"c-fat500-10"
			],
			"start_row": 16,
			"end_row": 16,
			"start_col": 0,
			"end_col": 0
		},
		{
			"id": 443,
			"tex": "(25)",
			"content": [
				"(25)"
			],
			"start_row": 44,
			"end_row": 44,
			"start_col": 9,
			"end_col": 9
		},
		{
			"id": 155,
			"tex": "126",
			"content": [
				"126"
			],
			"start_row": 16,
			"end_row": 16,
			"start_col": 1,
			"end_col": 1
		},
		{
			"id": 444,
			"tex": "p-hat300-3",
			"content": [
				"p-hat300-3"
			],
			"start_row": 45,
			"end_row": 45,
			"start_col": 0,
			"end_col": 0
		},
		{
			"id": 156,
			"tex": "0",
			"content": [
				"0"
			],
			"start_row": 16,
			"end_row": 16,
			"start_col": 2,
			"end_col": 2
		},
		{
			"id": 445,
			"tex": "3,829,005",
			"content": [
				"3,829,005"
			],
			"start_row": 45,
			"end_row": 45,
			"start_col": 1,
			"end_col": 1
		},
		{
			"id": 157,
			"tex": "(126)",
			"content": [
				"(126)"
			],
			"start_row": 16,
			"end_row": 16,
			"start_col": 3,
			"end_col": 3
		},
		{
			"id": 446,
			"tex": "74",
			"content": [
				"74"
			],
			"start_row": 45,
			"end_row": 45,
			"start_col": 2,
			"end_col": 2
		},
		{
			"id": 158,
			"tex": "126",
			"content": [
				"126"
			],
			"start_row": 16,
			"end_row": 16,
			"start_col": 4,
			"end_col": 4
		},
		{
			"id": 447,
			"tex": "(36)",
			"content": [
				"(36)"
			],
			"start_row": 45,
			"end_row": 45,
			"start_col": 3,
			"end_col": 3
		},
		{
			"id": 159,
			"tex": "0",
			"content": [
				"0"
			],
			"start_row": 16,
			"end_row": 16,
			"start_col": 5,
			"end_col": 5
		},
		{
			"id": 448,
			"tex": "624,947",
			"content": [
				"624,947"
			],
			"start_row": 45,
			"end_row": 45,
			"start_col": 4,
			"end_col": 4
		},
		{
			"id": 160,
			"tex": "(126)",
			"content": [
				"(126)"
			],
			"start_row": 16,
			"end_row": 16,
			"start_col": 6,
			"end_col": 6
		},
		{
			"id": 449,
			"tex": "\\bf{13}",
			"content": [
				"13"
			],
			"start_row": 45,
			"end_row": 45,
			"start_col": 5,
			"end_col": 5
		},
		{
			"id": 161,
			"tex": "126",
			"content": [
				"126"
			],
			"start_row": 16,
			"end_row": 16,
			"start_col": 7,
			"end_col": 7
		},
		{
			"id": 450,
			"tex": "(36)",
			"content": [
				"(36)"
			],
			"start_row": 45,
			"end_row": 45,
			"start_col": 6,
			"end_col": 6
		},
		{
			"id": 162,
			"tex": "0",
			"content": [
				"0"
			],
			"start_row": 16,
			"end_row": 16,
			"start_col": 8,
			"end_col": 8
		},
		{
			"id": 451,
			"tex": "713,107",
			"content": [
				"713,107"
			],
			"start_row": 45,
			"end_row": 45,
			"start_col": 7,
			"end_col": 7
		},
		{
			"id": 163,
			"tex": "(126)",
			"content": [
				"(126)"
			],
			"start_row": 16,
			"end_row": 16,
			"start_col": 9,
			"end_col": 9
		},
		{
			"id": 452,
			"tex": "21",
			"content": [
				"21"
			],
			"start_row": 45,
			"end_row": 45,
			"start_col": 8,
			"end_col": 8
		},
		{
			"id": 164,
			"tex": "c-fat500-1",
			"content": [
				"c-fat500-1"
			],
			"start_row": 17,
			"end_row": 17,
			"start_col": 0,
			"end_col": 0
		},
		{
			"id": 453,
			"tex": "(36)",
			"content": [
				"(36)"
			],
			"start_row": 45,
			"end_row": 45,
			"start_col": 9,
			"end_col": 9
		},
		{
			"id": 165,
			"tex": "14",
			"content": [
				"14"
			],
			"start_row": 17,
			"end_row": 17,
			"start_col": 1,
			"end_col": 1
		},
		{
			"id": 454,
			"tex": "p-hat500-1",
			"content": [
				"p-hat500-1"
			],
			"start_row": 46,
			"end_row": 46,
			"start_col": 0,
			"end_col": 0
		},
		{
			"id": 166,
			"tex": "0",
			"content": [
				"0"
			],
			"start_row": 17,
			"end_row": 17,
			"start_col": 2,
			"end_col": 2
		},
		{
			"id": 455,
			"tex": "12,907",
			"content": [
				"12,907"
			],
			"start_row": 46,
			"end_row": 46,
			"start_col": 1,
			"end_col": 1
		},
		{
			"id": 167,
			"tex": "(14)",
			"content": [
				"(14)"
			],
			"start_row": 17,
			"end_row": 17,
			"start_col": 3,
			"end_col": 3
		},
		{
			"id": 456,
			"tex": "0",
			"content": [
				"0"
			],
			"start_row": 46,
			"end_row": 46,
			"start_col": 2,
			"end_col": 2
		},
		{
			"id": 168,
			"tex": "14",
			"content": [
				"14"
			],
			"start_row": 17,
			"end_row": 17,
			"start_col": 4,
			"end_col": 4
		},
		{
			"id": 457,
			"tex": "(9)",
			"content": [
				"(9)"
			],
			"start_row": 46,
			"end_row": 46,
			"start_col": 3,
			"end_col": 3
		},
		{
			"id": 169,
			"tex": "0",
			"content": [
				"0"
			],
			"start_row": 17,
			"end_row": 17,
			"start_col": 5,
			"end_col": 5
		},
		{
			"id": 458,
			"tex": "9,777",
			"content": [
				"9,777"
			],
			"start_row": 46,
			"end_row": 46,
			"start_col": 4,
			"end_col": 4
		},
		{
			"id": 170,
			"tex": "(14)",
			"content": [
				"(14)"
			],
			"start_row": 17,
			"end_row": 17,
			"start_col": 6,
			"end_col": 6
		},
		{
			"id": 459,
			"tex": "0",
			"content": [
				"0"
			],
			"start_row": 46,
			"end_row": 46,
			"start_col": 5,
			"end_col": 5
		},
		{
			"id": 171,
			"tex": "14",
			"content": [
				"14"
			],
			"start_row": 17,
			"end_row": 17,
			"start_col": 7,
			"end_col": 7
		},
		{
			"id": 460,
			"tex": "(9)",
			"content": [
				"(9)"
			],
			"start_row": 46,
			"end_row": 46,
			"start_col": 6,
			"end_col": 6
		},
		{
			"id": 172,
			"tex": "0",
			"content": [
				"0"
			],
			"start_row": 17,
			"end_row": 17,
			"start_col": 8,
			"end_col": 8
		},
		{
			"id": 461,
			"tex": "8,608",
			"content": [
				"8,608"
			],
			"start_row": 46,
			"end_row": 46,
			"start_col": 7,
			"end_col": 7
		},
		{
			"id": 173,
			"tex": "(14)",
			"content": [
				"(14)"
			],
			"start_row": 17,
			"end_row": 17,
			"start_col": 9,
			"end_col": 9
		},
		{
			"id": 328,
			"tex": "38,019",
			"content": [
				"38,019"
			],
			"start_row": 33,
			"end_row": 33,
			"start_col": 4,
			"end_col": 4
		},
		{
			"id": 462,
			"tex": "0",
			"content": [
				"0"
			],
			"start_row": 46,
			"end_row": 46,
			"start_col": 8,
			"end_col": 8
		},
		{
			"id": 174,
			"tex": "c-fat500-2",
			"content": [
				"c-fat500-2"
			],
			"start_row": 18,
			"end_row": 18,
			"start_col": 0,
			"end_col": 0
		},
		{
			"id": 463,
			"tex": "(9)",
			"content": [
				"(9)"
			],
			"start_row": 46,
			"end_row": 46,
			"start_col": 9,
			"end_col": 9
		},
		{
			"id": 175,
			"tex": "26",
			"content": [
				"26"
			],
			"start_row": 18,
			"end_row": 18,
			"start_col": 1,
			"end_col": 1
		},
		{
			"id": 464,
			"tex": "p-hat500-2",
			"content": [
				"p-hat500-2"
			],
			"start_row": 47,
			"end_row": 47,
			"start_col": 0,
			"end_col": 0
		},
		{
			"id": 176,
			"tex": "0",
			"content": [
				"0"
			],
			"start_row": 18,
			"end_row": 18,
			"start_col": 2,
			"end_col": 2
		},
		{
			"id": 465,
			"tex": "1,022,190",
			"content": [
				"1,022,190"
			],
			"start_row": 47,
			"end_row": 47,
			"start_col": 1,
			"end_col": 1
		},
		{
			"id": 177,
			"tex": "(26)",
			"content": [
				"(26)"
			],
			"start_row": 18,
			"end_row": 18,
			"start_col": 3,
			"end_col": 3
		},
		{
			"id": 466,
			"tex": "23",
			"content": [
				"23"
			],
			"start_row": 47,
			"end_row": 47,
			"start_col": 2,
			"end_col": 2
		},
		{
			"id": 178,
			"tex": "26",
			"content": [
				"26"
			],
			"start_row": 18,
			"end_row": 18,
			"start_col": 4,
			"end_col": 4
		},
		{
			"id": 467,
			"tex": "(36)",
			"content": [
				"(36)"
			],
			"start_row": 47,
			"end_row": 47,
			"start_col": 3,
			"end_col": 3
		},
		{
			"id": 251,
			"tex": "33,629",
			"content": [
				"33,629"
			],
			"start_row": 25,
			"end_row": 25,
			"start_col": 7,
			"end_col": 7
		},
		{
			"id": 252,
			"tex": "0",
			"content": [
				"0"
			],
			"start_row": 25,
			"end_row": 25,
			"start_col": 8,
			"end_col": 8
		},
		{
			"id": 253,
			"tex": "(16)",
			"content": [
				"(16)"
			],
			"start_row": 25,
			"end_row": 25,
			"start_col": 9,
			"end_col": 9
		},
		{
			"id": 254,
			"tex": "johnson16-2-4",
			"content": [
				"johnson16-2-4"
			],
			"start_row": 26,
			"end_row": 26,
			"start_col": 0,
			"end_col": 0
		},
		{
			"id": 255,
			"tex": "323,036",
			"content": [
				"323,036"
			],
			"start_row": 26,
			"end_row": 26,
			"start_col": 1,
			"end_col": 1
		},
		{
			"id": 256,
			"tex": "0",
			"content": [
				"0"
			],
			"start_row": 26,
			"end_row": 26,
			"start_col": 2,
			"end_col": 2
		},
		{
			"id": 257,
			"tex": "(8)",
			"content": [
				"(8)"
			],
			"start_row": 26,
			"end_row": 26,
			"start_col": 3,
			"end_col": 3
		},
		{
			"id": 258,
			"tex": "256,100",
			"content": [
				"256,100"
			],
			"start_row": 26,
			"end_row": 26,
			"start_col": 4,
			"end_col": 4
		},
		{
			"id": 259,
			"tex": "0",
			"content": [
				"0"
			],
			"start_row": 26,
			"end_row": 26,
			"start_col": 5,
			"end_col": 5
		},
		{
			"id": 260,
			"tex": "(8)",
			"content": [
				"(8)"
			],
			"start_row": 26,
			"end_row": 26,
			"start_col": 6,
			"end_col": 6
		},
		{
			"id": 261,
			"tex": "256,100",
			"content": [
				"256,100"
			],
			"start_row": 26,
			"end_row": 26,
			"start_col": 7,
			"end_col": 7
		},
		{
			"id": 262,
			"tex": "0",
			"content": [
				"0"
			],
			"start_row": 26,
			"end_row": 26,
			"start_col": 8,
			"end_col": 8
		},
		{
			"id": 263,
			"tex": "(8)",
			"content": [
				"(8)"
			],
			"start_row": 26,
			"end_row": 26,
			"start_col": 9,
			"end_col": 9
		},
		{
			"id": 264,
			"tex": "johnson32-2-4",
			"content": [
				"johnson32-2-4"
			],
			"start_row": 27,
			"end_row": 27,
			"start_col": 0,
			"end_col": 0
		},
		{
			"id": 265,
			"tex": "10,447,210,976",
			"content": [
				"10,447,210,976"
			],
			"start_row": 27,
			"end_row": 27,
			"start_col": 1,
			"end_col": 1
		},
		{
			"id": 266,
			"tex": "---",
			"content": [
				"\u2014"
			],
			"start_row": 27,
			"end_row": 27,
			"start_col": 2,
			"end_col": 2
		},
		{
			"id": 267,
			"tex": "(16)",
			"content": [
				"(16)"
			],
			"start_row": 27,
			"end_row": 27,
			"start_col": 3,
			"end_col": 3
		},
		{
			"id": 268,
			"tex": "8,269,639,389",
			"content": [
				"8,269,639,389"
			],
			"start_row": 27,
			"end_row": 27,
			"start_col": 4,
			"end_col": 4
		},
		{
			"id": 269,
			"tex": "---",
			"content": [
				"\u2014"
			],
			"start_row": 27,
			"end_row": 27,
			"start_col": 5,
			"end_col": 5
		},
		{
			"id": 270,
			"tex": "(16)",
			"content": [
				"(16)"
			],
			"start_row": 27,
			"end_row": 27,
			"start_col": 6,
			"end_col": 6
		},
		{
			"id": 271,
			"tex": "7,345,343,221",
			"content": [
				"7,345,343,221"
			],
			"start_row": 27,
			"end_row": 27,
			"start_col": 7,
			"end_col": 7
		},
		{
			"id": 272,
			"tex": "---",
			"content": [
				"\u2014"
			],
			"start_row": 27,
			"end_row": 27,
			"start_col": 8,
			"end_col": 8
		},
		{
			"id": 273,
			"tex": "(16)",
			"content": [
				"(16)"
			],
			"start_row": 27,
			"end_row": 27,
			"start_col": 9,
			"end_col": 9
		},
		{
			"id": 274,
			"tex": "johnson8-2-4",
			"content": [
				"johnson8-2-4"
			],
			"start_row": 28,
			"end_row": 28,
			"start_col": 0,
			"end_col": 0
		},
		{
			"id": 275,
			"tex": "36",
			"content": [
				"36"
			],
			"start_row": 28,
			"end_row": 28,
			"start_col": 1,
			"end_col": 1
		},
		{
			"id": 276,
			"tex": "0",
			"content": [
				"0"
			],
			"start_row": 28,
			"end_row": 28,
			"start_col": 2,
			"end_col": 2
		},
		{
			"id": 277,
			"tex": "(4)",
			"content": [
				"(4)"
			],
			"start_row": 28,
			"end_row": 28,
			"start_col": 3,
			"end_col": 3
		},
		{
			"id": 278,
			"tex": "24",
			"content": [
				"24"
			],
			"start_row": 28,
			"end_row": 28,
			"start_col": 4,
			"end_col": 4
		},
		{
			"id": 279,
			"tex": "0",
			"content": [
				"0"
			],
			"start_row": 28,
			"end_row": 28,
			"start_col": 5,
			"end_col": 5
		},
		{
			"id": 280,
			"tex": "(4)",
			"content": [
				"(4)"
			],
			"start_row": 28,
			"end_row": 28,
			"start_col": 6,
			"end_col": 6
		},
		{
			"id": 281,
			"tex": "24",
			"content": [
				"24"
			],
			"start_row": 28,
			"end_row": 28,
			"start_col": 7,
			"end_col": 7
		},
		{
			"id": 282,
			"tex": "0",
			"content": [
				"0"
			],
			"start_row": 28,
			"end_row": 28,
			"start_col": 8,
			"end_col": 8
		},
		{
			"id": 283,
			"tex": "(4)",
			"content": [
				"(4)"
			],
			"start_row": 28,
			"end_row": 28,
			"start_col": 9,
			"end_col": 9
		},
		{
			"id": 284,
			"tex": "johnson8-4-4",
			"content": [
				"johnson8-4-4"
			],
			"start_row": 29,
			"end_row": 29,
			"start_col": 0,
			"end_col": 0
		},
		{
			"id": 285,
			"tex": "144",
			"content": [
				"144"
			],
			"start_row": 29,
			"end_row": 29,
			"start_col": 1,
			"end_col": 1
		},
		{
			"id": 286,
			"tex": "0",
			"content": [
				"0"
			],
			"start_row": 29,
			"end_row": 29,
			"start_col": 2,
			"end_col": 2
		},
		{
			"id": 287,
			"tex": "(14)",
			"content": [
				"(14)"
			],
			"start_row": 29,
			"end_row": 29,
			"start_col": 3,
			"end_col": 3
		},
		{
			"id": 288,
			"tex": "126",
			"content": [
				"126"
			],
			"start_row": 29,
			"end_row": 29,
			"start_col": 4,
			"end_col": 4
		},
		{
			"id": 289,
			"tex": "0",
			"content": [
				"0"
			],
			"start_row": 29,
			"end_row": 29,
			"start_col": 5,
			"end_col": 5
		},
		{
			"id": 290,
			"tex": "(14)",
			"content": [
				"(14)"
			],
			"start_row": 29,
			"end_row": 29,
			"start_col": 6,
			"end_col": 6
		},
		{
			"id": 291,
			"tex": "126",
			"content": [
				"126"
			],
			"start_row": 29,
			"end_row": 29,
			"start_col": 7,
			"end_col": 7
		},
		{
			"id": 292,
			"tex": "0",
			"content": [
				"0"
			],
			"start_row": 29,
			"end_row": 29,
			"start_col": 8,
			"end_col": 8
		},
		{
			"id": 293,
			"tex": "(14)",
			"content": [
				"(14)"
			],
			"start_row": 29,
			"end_row": 29,
			"start_col": 9,
			"end_col": 9
		},
		{
			"id": 294,
			"tex": "keller4",
			"content": [
				"keller4"
			],
			"start_row": 30,
			"end_row": 30,
			"start_col": 0,
			"end_col": 0
		},
		{
			"id": 295,
			"tex": "13,113",
			"content": [
				"13,113"
			],
			"start_row": 30,
			"end_row": 30,
			"start_col": 1,
			"end_col": 1
		},
		{
			"id": 296,
			"tex": "0",
			"content": [
				"0"
			],
			"start_row": 30,
			"end_row": 30,
			"start_col": 2,
			"end_col": 2
		},
		{
			"id": 297,
			"tex": "(11)",
			"content": [
				"(11)"
			],
			"start_row": 30,
			"end_row": 30,
			"start_col": 3,
			"end_col": 3
		},
		{
			"id": 298,
			"tex": "13,725",
			"content": [
				"13,725"
			],
			"start_row": 30,
			"end_row": 30,
			"start_col": 4,
			"end_col": 4
		},
		{
			"id": 299,
			"tex": "0",
			"content": [
				"0"
			],
			"start_row": 30,
			"end_row": 30,
			"start_col": 5,
			"end_col": 5
		},
		{
			"id": 300,
			"tex": "(11)",
			"content": [
				"(11)"
			],
			"start_row": 30,
			"end_row": 30,
			"start_col": 6,
			"end_col": 6
		},
		{
			"id": 301,
			"tex": "10,470",
			"content": [
				"10,470"
			],
			"start_row": 30,
			"end_row": 30,
			"start_col": 7,
			"end_col": 7
		},
		{
			"id": 302,
			"tex": "0",
			"content": [
				"0"
			],
			"start_row": 30,
			"end_row": 30,
			"start_col": 8,
			"end_col": 8
		},
		{
			"id": 303,
			"tex": "(11)",
			"content": [
				"(11)"
			],
			"start_row": 30,
			"end_row": 30,
			"start_col": 9,
			"end_col": 9
		},
		{
			"id": 304,
			"tex": "keller5",
			"content": [
				"keller5"
			],
			"start_row": 31,
			"end_row": 31,
			"start_col": 0,
			"end_col": 0
		},
		{
			"id": 305,
			"tex": "603,233,453",
			"content": [
				"603,233,453"
			],
			"start_row": 31,
			"end_row": 31,
			"start_col": 1,
			"end_col": 1
		},
		{
			"id": 306,
			"tex": "---",
			"content": [
				"\u2014"
			],
			"start_row": 31,
			"end_row": 31,
			"start_col": 2,
			"end_col": 2
		},
		{
			"id": 307,
			"tex": "(27)",
			"content": [
				"(27)"
			],
			"start_row": 31,
			"end_row": 31,
			"start_col": 3,
			"end_col": 3
		},
		{
			"id": 308,
			"tex": "596,150,386",
			"content": [
				"596,150,386"
			],
			"start_row": 31,
			"end_row": 31,
			"start_col": 4,
			"end_col": 4
		},
		{
			"id": 309,
			"tex": "---",
			"content": [
				"\u2014"
			],
			"start_row": 31,
			"end_row": 31,
			"start_col": 5,
			"end_col": 5
		},
		{
			"id": 310,
			"tex": "(27)",
			"content": [
				"(27)"
			],
			"start_row": 31,
			"end_row": 31,
			"start_col": 6,
			"end_col": 6
		},
		{
			"id": 311,
			"tex": "523,346,613",
			"content": [
				"523,346,613"
			],
			"start_row": 31,
			"end_row": 31,
			"start_col": 7,
			"end_col": 7
		},
		{
			"id": 312,
			"tex": "---",
			"content": [
				"\u2014"
			],
			"start_row": 31,
			"end_row": 31,
			"start_col": 8,
			"end_col": 8
		},
		{
			"id": 313,
			"tex": "(27)",
			"content": [
				"(27)"
			],
			"start_row": 31,
			"end_row": 31,
			"start_col": 9,
			"end_col": 9
		},
		{
			"id": 314,
			"tex": "keller6",
			"content": [
				"keller6"
			],
			"start_row": 32,
			"end_row": 32,
			"start_col": 0,
			"end_col": 0
		},
		{
			"id": 315,
			"tex": "285,704,599",
			"content": [
				"285,704,599"
			],
			"start_row": 32,
			"end_row": 32,
			"start_col": 1,
			"end_col": 1
		},
		{
			"id": 316,
			"tex": "---",
			"content": [
				"\u2014"
			],
			"start_row": 32,
			"end_row": 32,
			"start_col": 2,
			"end_col": 2
		},
		{
			"id": 317,
			"tex": "(48)",
			"content": [
				"(48)"
			],
			"start_row": 32,
			"end_row": 32,
			"start_col": 3,
			"end_col": 3
		},
		{
			"id": 318,
			"tex": "226,330,037",
			"content": [
				"226,330,037"
			],
			"start_row": 32,
			"end_row": 32,
			"start_col": 4,
			"end_col": 4
		},
		{
			"id": 319,
			"tex": "---",
			"content": [
				"\u2014"
			],
			"start_row": 32,
			"end_row": 32,
			"start_col": 5,
			"end_col": 5
		},
		{
			"id": 320,
			"tex": "(52)",
			"content": [
				"(52)"
			],
			"start_row": 32,
			"end_row": 32,
			"start_col": 6,
			"end_col": 6
		},
		{
			"id": 321,
			"tex": "240,958,450",
			"content": [
				"240,958,450"
			],
			"start_row": 32,
			"end_row": 32,
			"start_col": 7,
			"end_col": 7
		},
		{
			"id": 322,
			"tex": "---",
			"content": [
				"\u2014"
			],
			"start_row": 32,
			"end_row": 32,
			"start_col": 8,
			"end_col": 8
		},
		{
			"id": 612,
			"tex": "\\bf{5}",
			"content": [
				"5"
			],
			"start_row": 61,
			"end_row": 61,
			"start_col": 8,
			"end_col": 8
		},
		{
			"id": 613,
			"tex": "(22)",
			"content": [
				"(22)"
			],
			"start_row": 61,
			"end_row": 61,
			"start_col": 9,
			"end_col": 9
		},
		{
			"id": 614,
			"tex": "san400-0.9-1",
			"content": [
				"san400-0.9-1"
			],
			"start_row": 62,
			"end_row": 62,
			"start_col": 0,
			"end_col": 0
		},
		{
			"id": 615,
			"tex": "523,531,417",
			"content": [
				"523,531,417"
			],
			"start_row": 62,
			"end_row": 62,
			"start_col": 1,
			"end_col": 1
		},
		{
			"id": 616,
			"tex": "---",
			"content": [
				"\u2014"
			],
			"start_row": 62,
			"end_row": 62,
			"start_col": 2,
			"end_col": 2
		},
		{
			"id": 617,
			"tex": "(56)",
			"content": [
				"(56)"
			],
			"start_row": 62,
			"end_row": 62,
			"start_col": 3,
			"end_col": 3
		},
		{
			"id": 618,
			"tex": "4,536,723",
			"content": [
				"4,536,723"
			],
			"start_row": 62,
			"end_row": 62,
			"start_col": 4,
			"end_col": 4
		},
		{
			"id": 619,
			"tex": "422",
			"content": [
				"422"
			],
			"start_row": 62,
			"end_row": 62,
			"start_col": 5,
			"end_col": 5
		},
		{
			"id": 620,
			"tex": "(100)",
			"content": [
				"(100)"
			],
			"start_row": 62,
			"end_row": 62,
			"start_col": 6,
			"end_col": 6
		},
		{
			"id": 621,
			"tex": "582,445",
			"content": [
				"582,445"
			],
			"start_row": 62,
			"end_row": 62,
			"start_col": 7,
			"end_col": 7
		},
		{
			"id": 622,
			"tex": "\\bf{54}",
			"content": [
				"54"
			],
			"start_row": 62,
			"end_row": 62,
			"start_col": 8,
			"end_col": 8
		},
		{
			"id": 623,
			"tex": "(100)",
			"content": [
				"(100)"
			],
			"start_row": 62,
			"end_row": 62,
			"start_col": 9,
			"end_col": 9
		},
		{
			"id": 624,
			"tex": "sanr200-0.7",
			"content": [
				"sanr200-0.7"
			],
			"start_row": 63,
			"end_row": 63,
			"start_col": 0,
			"end_col": 0
		},
		{
			"id": 625,
			"tex": "206,262",
			"content": [
				"206,262"
			],
			"start_row": 63,
			"end_row": 63,
			"start_col": 1,
			"end_col": 1
		},
		{
			"id": 626,
			"tex": "1",
			"content": [
				"1"
			],
			"start_row": 63,
			"end_row": 63,
			"start_col": 2,
			"end_col": 2
		},
		{
			"id": 627,
			"tex": "(18)",
			"content": [
				"(18)"
			],
			"start_row": 63,
			"end_row": 63,
			"start_col": 3,
			"end_col": 3
		},
		{
			"id": 628,
			"tex": "152,882",
			"content": [
				"152,882"
			],
			"start_row": 63,
			"end_row": 63,
			"start_col": 4,
			"end_col": 4
		},
		{
			"id": 629,
			"tex": "1",
			"content": [
				"1"
			],
			"start_row": 63,
			"end_row": 63,
			"start_col": 5,
			"end_col": 5
		},
		{
			"id": 630,
			"tex": "(18)",
			"content": [
				"(18)"
			],
			"start_row": 63,
			"end_row": 63,
			"start_col": 6,
			"end_col": 6
		},
		{
			"id": 631,
			"tex": "100,977",
			"content": [
				"100,977"
			],
			"start_row": 63,
			"end_row": 63,
			"start_col": 7,
			"end_col": 7
		},
		{
			"id": 632,
			"tex": "1",
			"content": [
				"1"
			],
			"start_row": 63,
			"end_row": 63,
			"start_col": 8,
			"end_col": 8
		},
		{
			"id": 633,
			"tex": "(18)",
			"content": [
				"(18)"
			],
			"start_row": 63,
			"end_row": 63,
			"start_col": 9,
			"end_col": 9
		},
		{
			"id": 634,
			"tex": "sanr200-0.9",
			"content": [
				"sanr200-0.9"
			],
			"start_row": 64,
			"end_row": 64,
			"start_col": 0,
			"end_col": 0
		},
		{
			"id": 635,
			"tex": "44,472,276",
			"content": [
				"44,472,276"
			],
			"start_row": 64,
			"end_row": 64,
			"start_col": 1,
			"end_col": 1
		},
		{
			"id": 636,
			"tex": "892",
			"content": [
				"892"
			],
			"start_row": 64,
			"end_row": 64,
			"start_col": 2,
			"end_col": 2
		},
		{
			"id": 637,
			"tex": "(42)",
			"content": [
				"(42)"
			],
			"start_row": 64,
			"end_row": 64,
			"start_col": 3,
			"end_col": 3
		},
		{
			"id": 638,
			"tex": "14,921,850",
			"content": [
				"14,921,850"
			],
			"start_row": 64,
			"end_row": 64,
			"start_col": 4,
			"end_col": 4
		},
		{
			"id": 639,
			"tex": "283",
			"content": [
				"283"
			],
			"start_row": 64,
			"end_row": 64,
			"start_col": 5,
			"end_col": 5
		},
		{
			"id": 640,
			"tex": "(42)",
			"content": [
				"(42)"
			],
			"start_row": 64,
			"end_row": 64,
			"start_col": 6,
			"end_col": 6
		},
		{
			"id": 641,
			"tex": "9,730,778",
			"content": [
				"9,730,778"
			],
			"start_row": 64,
			"end_row": 64,
			"start_col": 7,
			"end_col": 7
		},
		{
			"id": 642,
			"tex": "\\bf{245}",
			"content": [
				"245"
			],
			"start_row": 64,
			"end_row": 64,
			"start_col": 8,
			"end_col": 8
		},
		{
			"id": 643,
			"tex": "(42)",
			"content": [
				"(42)"
			],
			"start_row": 64,
			"end_row": 64,
			"start_col": 9,
			"end_col": 9
		},
		{
			"id": 644,
			"tex": "sanr400-0.5",
			"content": [
				"sanr400-0.5"
			],
			"start_row": 65,
			"end_row": 65,
			"start_col": 0,
			"end_col": 0
		},
		{
			"id": 645,
			"tex": "380,151",
			"content": [
				"380,151"
			],
			"start_row": 65,
			"end_row": 65,
			"start_col": 1,
			"end_col": 1
		},
		{
			"id": 646,
			"tex": "2",
			"content": [
				"2"
			],
			"start_row": 65,
			"end_row": 65,
			"start_col": 2,
			"end_col": 2
		},
		{
			"id": 647,
			"tex": "(13)",
			"content": [
				"(13)"
			],
			"start_row": 65,
			"end_row": 65,
			"start_col": 3,
			"end_col": 3
		},
		{
			"id": 648,
			"tex": "320,110",
			"content": [
				"320,110"
			],
			"start_row": 65,
			"end_row": 65,
			"start_col": 4,
			"end_col": 4
		},
		{
			"id": 649,
			"tex": "2",
			"content": [
				"2"
			],
			"start_row": 65,
			"end_row": 65,
			"start_col": 5,
			"end_col": 5
		},
		{
			"id": 650,
			"tex": "(13)",
			"content": [
				"(13)"
			],
			"start_row": 65,
			"end_row": 65,
			"start_col": 6,
			"end_col": 6
		},
		{
			"id": 651,
			"tex": "190,706",
			"content": [
				"190,706"
			],
			"start_row": 65,
			"end_row": 65,
			"start_col": 7,
			"end_col": 7
		},
		{
			"id": 652,
			"tex": "2",
			"content": [
				"2"
			],
			"start_row": 65,
			"end_row": 65,
			"start_col": 8,
			"end_col": 8
		},
		{
			"id": 653,
			"tex": "(13)",
			"content": [
				"(13)"
			],
			"start_row": 65,
			"end_row": 65,
			"start_col": 9,
			"end_col": 9
		},
		{
			"id": 654,
			"tex": "sanr400-0.7",
			"content": [
				"sanr400-0.7"
			],
			"start_row": 66,
			"end_row": 66,
			"start_col": 0,
			"end_col": 0
		},
		{
			"id": 655,
			"tex": "101,213,527",
			"content": [
				"101,213,527"
			],
			"start_row": 66,
			"end_row": 66,
			"start_col": 1,
			"end_col": 1
		},
		{
			"id": 656,
			"tex": "979",
			"content": [
				"979"
			],
			"start_row": 66,
			"end_row": 66,
			"start_col": 2,
			"end_col": 2
		},
		{
			"id": 657,
			"tex": "(21)",
			"content": [
				"(21)"
			],
			"start_row": 66,
			"end_row": 66,
			"start_col": 3,
			"end_col": 3
		},
		{
			"id": 658,
			"tex": "64,412,015",
			"content": [
				"64,412,015"
			],
			"start_row": 66,
			"end_row": 66,
			"start_col": 4,
			"end_col": 4
		},
		{
			"id": 659,
			"tex": "711",
			"content": [
				"711"
			],
			"start_row": 66,
			"end_row": 66,
			"start_col": 5,
			"end_col": 5
		},
		{
			"id": 660,
			"tex": "(21)",
			"content": [
				"(21)"
			],
			"start_row": 66,
			"end_row": 66,
			"start_col": 6,
			"end_col": 6
		},
		{
			"id": 661,
			"tex": "46,125,168",
			"content": [
				"46,125,168"
			],
			"start_row": 66,
			"end_row": 66,
			"start_col": 7,
			"end_col": 7
		},
		{
			"id": 662,
			"tex": "\\bf{650}",
			"content": [
				"650"
			],
			"start_row": 66,
			"end_row": 66,
			"start_col": 8,
			"end_col": 8
		},
		{
			"id": 663,
			"tex": "(21)",
			"content": [
				"(21)"
			],
			"start_row": 66,
			"end_row": 66,
			"start_col": 9,
			"end_col": 9
		}
	]
}