{
	"cells": [
		{
			"id": 31,
			"tex": "{\\bf 0.454 ($\\pm$0.027)}",
			"content": [
				"0.454",
				"(\u00b10.027)"
			],
			"start_row": 6,
			"end_row": 6,
			"start_col": 3,
			"end_col": 3
		},
		{
			"id": 33,
			"tex": "Greedy",
			"content": [
				"Greedy"
			],
			"start_row": 7,
			"end_row": 7,
			"start_col": 0,
			"end_col": 0
		},
		{
			"id": 21,
			"tex": "($\\pm$ Std Error)",
			"content": [
				"(\u00b1",
				"Std",
				"Error)"
			],
			"start_row": 4,
			"end_row": 4,
			"start_col": 3,
			"end_col": 3
		},
		{
			"id": 6,
			"tex": "\\textsc{Maximal}",
			"content": [
				"Maximal"
			],
			"start_row": 1,
			"end_row": 1,
			"start_col": 3,
			"end_col": 3
		},
		{
			"id": 34,
			"tex": "{\\bf 101.969 ($\\pm$0.429)}",
			"content": [
				"101.969",
				"(\u00b10.429)"
			],
			"start_row": 7,
			"end_row": 7,
			"start_col": 1,
			"end_col": 1
		},
		{
			"id": 48,
			"tex": "\\textsc{Ground truth}",
			"content": [
				"Ground",
				"truth"
			],
			"start_row": 10,
			"end_row": 10,
			"start_col": 0,
			"end_col": 0
		},
		{
			"id": 5,
			"tex": "\\textsc{Minimal}",
			"content": [
				"Minimal"
			],
			"start_row": 1,
			"end_row": 1,
			"start_col": 2,
			"end_col": 2
		},
		{
			"id": 40,
			"tex": "113.285 ($\\pm$2.305)",
			"content": [
				"113.285",
				"(\u00b12.305)"
			],
			"start_row": 8,
			"end_row": 8,
			"start_col": 2,
			"end_col": 2
		},
		{
			"id": 42,
			"tex": "0.394 ($\\pm$0.023)",
			"content": [
				"0.394",
				"(\u00b10.023)"
			],
			"start_row": 8,
			"end_row": 8,
			"start_col": 4,
			"end_col": 4
		},
		{
			"id": 46,
			"tex": "0.407 ($\\pm$0.025)",
			"content": [
				"0.407",
				"(\u00b10.025)"
			],
			"start_row": 9,
			"end_row": 9,
			"start_col": 3,
			"end_col": 3
		},
		{
			"id": 44,
			"tex": "114.894 ($\\pm$2.452)",
			"content": [
				"114.894",
				"(\u00b12.452)"
			],
			"start_row": 9,
			"end_row": 9,
			"start_col": 1,
			"end_col": 1
		},
		{
			"id": 11,
			"tex": "\\textsc{Connection}",
			"content": [
				"Connection"
			],
			"start_row": 2,
			"end_row": 2,
			"start_col": 3,
			"end_col": 3
		},
		{
			"id": 15,
			"tex": "Average",
			"content": [
				"Average"
			],
			"start_row": 3,
			"end_row": 3,
			"start_col": 2,
			"end_col": 2
		},
		{
			"id": 17,
			"tex": "Average",
			"content": [
				"Average"
			],
			"start_row": 3,
			"end_row": 3,
			"start_col": 4,
			"end_col": 4
		},
		{
			"id": 25,
			"tex": "130.998 ($\\pm$2.917)",
			"content": [
				"130.998",
				"(\u00b12.917)"
			],
			"start_row": 5,
			"end_row": 5,
			"start_col": 2,
			"end_col": 2
		},
		{
			"id": 27,
			"tex": "0.360 ($\\pm$0.023)",
			"content": [
				"0.360",
				"(\u00b10.023)"
			],
			"start_row": 5,
			"end_row": 5,
			"start_col": 4,
			"end_col": 4
		},
		{
			"id": 37,
			"tex": "0.426 ($\\pm$0.026)",
			"content": [
				"0.426",
				"(\u00b10.026)"
			],
			"start_row": 7,
			"end_row": 7,
			"start_col": 4,
			"end_col": 4
		},
		{
			"id": 4,
			"tex": "\\textsc{Maximal}",
			"content": [
				"Maximal"
			],
			"start_row": 1,
			"end_row": 1,
			"start_col": 1,
			"end_col": 1
		},
		{
			"id": 14,
			"tex": "Average",
			"content": [
				"Average"
			],
			"start_row": 3,
			"end_row": 3,
			"start_col": 1,
			"end_col": 1
		},
		{
			"id": 41,
			"tex": "0.411\n($\\pm$0.024)",
			"content": [
				"0.411",
				"(\u00b10.024)"
			],
			"start_row": 8,
			"end_row": 8,
			"start_col": 3,
			"end_col": 3
		},
		{
			"id": 1,
			"tex": "\\textsc{Distance-cost ratio}",
			"content": [
				"Distance-cost",
				"ratio"
			],
			"start_row": 0,
			"end_row": 0,
			"start_col": 1,
			"end_col": 2
		},
		{
			"id": 12,
			"tex": "\\textsc{Connection}",
			"content": [
				"Connection"
			],
			"start_row": 2,
			"end_row": 2,
			"start_col": 4,
			"end_col": 4
		},
		{
			"id": 7,
			"tex": "\\textsc{Minimal}",
			"content": [
				"Minimal"
			],
			"start_row": 1,
			"end_row": 1,
			"start_col": 4,
			"end_col": 4
		},
		{
			"id": 28,
			"tex": "Hitting-distance",
			"content": [
				"Hitting-distance"
			],
			"start_row": 6,
			"end_row": 6,
			"start_col": 0,
			"end_col": 0
		},
		{
			"id": 19,
			"tex": "($\\pm$ Std Error)",
			"content": [
				"(\u00b1",
				"Std",
				"Error)"
			],
			"start_row": 4,
			"end_row": 4,
			"start_col": 1,
			"end_col": 1
		},
		{
			"id": 36,
			"tex": "0.428\n($\\pm$0.025)",
			"content": [
				"0.428",
				"(\u00b10.025)"
			],
			"start_row": 7,
			"end_row": 7,
			"start_col": 3,
			"end_col": 3
		},
		{
			"id": 30,
			"tex": "105.797\n($\\pm$2.322)",
			"content": [
				"105.797",
				"(\u00b12.322)"
			],
			"start_row": 6,
			"end_row": 6,
			"start_col": 2,
			"end_col": 2
		},
		{
			"id": 45,
			"tex": "112.392 ($\\pm$2.266)",
			"content": [
				"112.392",
				"(\u00b12.266)"
			],
			"start_row": 9,
			"end_row": 9,
			"start_col": 2,
			"end_col": 2
		},
		{
			"id": 38,
			"tex": "Degree based",
			"content": [
				"Degree",
				"based"
			],
			"start_row": 8,
			"end_row": 8,
			"start_col": 0,
			"end_col": 0
		},
		{
			"id": 0,
			"tex": "",
			"content": [],
			"start_row": 0,
			"end_row": 0,
			"start_col": 0,
			"end_col": 0
		},
		{
			"id": 13,
			"tex": "",
			"content": [],
			"start_row": 3,
			"end_row": 3,
			"start_col": 0,
			"end_col": 0
		},
		{
			"id": 50,
			"tex": "119.243 ($\\pm$1.873)",
			"content": [
				"119.243",
				"(\u00b11.873)"
			],
			"start_row": 10,
			"end_row": 10,
			"start_col": 2,
			"end_col": 2
		},
		{
			"id": 39,
			"tex": "114.182 ($\\pm$2.386)",
			"content": [
				"114.182",
				"(\u00b12.386)"
			],
			"start_row": 8,
			"end_row": 8,
			"start_col": 1,
			"end_col": 1
		},
		{
			"id": 24,
			"tex": "122.747($\\pm$2.812)",
			"content": [
				"122.747(\u00b12.812)"
			],
			"start_row": 5,
			"end_row": 5,
			"start_col": 1,
			"end_col": 1
		},
		{
			"id": 9,
			"tex": "\\textsc{Connection}",
			"content": [
				"Connection"
			],
			"start_row": 2,
			"end_row": 2,
			"start_col": 1,
			"end_col": 1
		},
		{
			"id": 22,
			"tex": "($\\pm$ Std Error)",
			"content": [
				"(\u00b1",
				"Std",
				"Error)"
			],
			"start_row": 4,
			"end_row": 4,
			"start_col": 4,
			"end_col": 4
		},
		{
			"id": 23,
			"tex": "Spanning-tree",
			"content": [
				"Spanning-tree"
			],
			"start_row": 5,
			"end_row": 5,
			"start_col": 0,
			"end_col": 0
		},
		{
			"id": 32,
			"tex": "{\\bf 0.459 ($\\pm$0.027)}",
			"content": [
				"0.459",
				"(\u00b10.027)"
			],
			"start_row": 6,
			"end_row": 6,
			"start_col": 4,
			"end_col": 4
		},
		{
			"id": 29,
			"tex": "103.945 ($\\pm$1.320)",
			"content": [
				"103.945",
				"(\u00b11.320)"
			],
			"start_row": 6,
			"end_row": 6,
			"start_col": 1,
			"end_col": 1
		},
		{
			"id": 20,
			"tex": "($\\pm$ Std Error)",
			"content": [
				"(\u00b1",
				"Std",
				"Error)"
			],
			"start_row": 4,
			"end_row": 4,
			"start_col": 2,
			"end_col": 2
		},
		{
			"id": 26,
			"tex": "0.369 ($\\pm$0.023)",
			"content": [
				"0.369",
				"(\u00b10.023)"
			],
			"start_row": 5,
			"end_row": 5,
			"start_col": 3,
			"end_col": 3
		},
		{
			"id": 49,
			"tex": "115.117 ($\\pm$1.782)",
			"content": [
				"115.117",
				"(\u00b11.782)"
			],
			"start_row": 10,
			"end_row": 10,
			"start_col": 1,
			"end_col": 1
		},
		{
			"id": 47,
			"tex": "0.398 ($\\pm$0.023)",
			"content": [
				"0.398",
				"(\u00b10.023)"
			],
			"start_row": 9,
			"end_row": 9,
			"start_col": 4,
			"end_col": 4
		},
		{
			"id": 3,
			"tex": "",
			"content": [],
			"start_row": 1,
			"end_row": 1,
			"start_col": 0,
			"end_col": 0
		},
		{
			"id": 8,
			"tex": "",
			"content": [],
			"start_row": 2,
			"end_row": 2,
			"start_col": 0,
			"end_col": 0
		},
		{
			"id": 43,
			"tex": "PageRank based",
			"content": [
				"PageRank",
				"based"
			],
			"start_row": 9,
			"end_row": 9,
			"start_col": 0,
			"end_col": 0
		},
		{
			"id": 18,
			"tex": "\\textsc{Heuristic}",
			"content": [
				"Heuristic"
			],
			"start_row": 4,
			"end_row": 4,
			"start_col": 0,
			"end_col": 0
		},
		{
			"id": 16,
			"tex": "Average",
			"content": [
				"Average"
			],
			"start_row": 3,
			"end_row": 3,
			"start_col": 3,
			"end_col": 3
		},
		{
			"id": 10,
			"tex": "\\textsc{Connection}",
			"content": [
				"Connection"
			],
			"start_row": 2,
			"end_row": 2,
			"start_col": 2,
			"end_col": 2
		},
		{
			"id": 2,
			"tex": "\\textsc{Value}",
			"content": [
				"Value"
			],
			"start_row": 0,
			"end_row": 0,
			"start_col": 3,
			"end_col": 4
		},
		{
			"id": 35,
			"tex": "{\\bf 102.785 ($\\pm$ 0.426)}",
			"content": [
				"102.785",
				"(\u00b1",
				"0.426)"
			],
			"start_row": 7,
			"end_row": 7,
			"start_col": 2,
			"end_col": 2
		}
	]
}