{
	"cells": [
		{
			"id": 60,
			"tex": "75",
			"content": [
				"75"
			],
			"start_row": 8,
			"end_row": 8,
			"start_col": 4,
			"end_col": 4
		},
		{
			"id": 1,
			"tex": "\\# snarks",
			"content": [
				"#",
				"snarks"
			],
			"start_row": 0,
			"end_row": 0,
			"start_col": 1,
			"end_col": 1
		},
		{
			"id": 61,
			"tex": "1",
			"content": [
				"1"
			],
			"start_row": 8,
			"end_row": 8,
			"start_col": 5,
			"end_col": 5
		},
		{
			"id": 6,
			"tex": "$\\lambda_c \\geq 6$",
			"content": [
				"\u03bbc",
				"\u2265",
				"6"
			],
			"start_row": 0,
			"end_row": 0,
			"start_col": 6,
			"end_col": 6
		},
		{
			"id": 62,
			"tex": "1",
			"content": [
				"1"
			],
			"start_row": 8,
			"end_row": 8,
			"start_col": 6,
			"end_col": 6
		},
		{
			"id": 63,
			"tex": "30",
			"content": [
				"30"
			],
			"start_row": 9,
			"end_row": 9,
			"start_col": 0,
			"end_col": 0
		},
		{
			"id": 10,
			"tex": "0",
			"content": [
				"0"
			],
			"start_row": 1,
			"end_row": 1,
			"start_col": 3,
			"end_col": 3
		},
		{
			"id": 64,
			"tex": "28 399",
			"content": [
				"28",
				"399"
			],
			"start_row": 9,
			"end_row": 9,
			"start_col": 1,
			"end_col": 1
		},
		{
			"id": 65,
			"tex": "1",
			"content": [
				"1"
			],
			"start_row": 9,
			"end_row": 9,
			"start_col": 2,
			"end_col": 2
		},
		{
			"id": 66,
			"tex": "0",
			"content": [
				"0"
			],
			"start_row": 9,
			"end_row": 9,
			"start_col": 3,
			"end_col": 3
		},
		{
			"id": 67,
			"tex": "509",
			"content": [
				"509"
			],
			"start_row": 9,
			"end_row": 9,
			"start_col": 4,
			"end_col": 4
		},
		{
			"id": 68,
			"tex": "1",
			"content": [
				"1"
			],
			"start_row": 9,
			"end_row": 9,
			"start_col": 5,
			"end_col": 5
		},
		{
			"id": 69,
			"tex": "0",
			"content": [
				"0"
			],
			"start_row": 9,
			"end_row": 9,
			"start_col": 6,
			"end_col": 6
		},
		{
			"id": 70,
			"tex": "32",
			"content": [
				"32"
			],
			"start_row": 10,
			"end_row": 10,
			"start_col": 0,
			"end_col": 0
		},
		{
			"id": 71,
			"tex": "293 059",
			"content": [
				"293",
				"059"
			],
			"start_row": 10,
			"end_row": 10,
			"start_col": 1,
			"end_col": 1
		},
		{
			"id": 72,
			"tex": "0",
			"content": [
				"0"
			],
			"start_row": 10,
			"end_row": 10,
			"start_col": 2,
			"end_col": 2
		},
		{
			"id": 73,
			"tex": "0",
			"content": [
				"0"
			],
			"start_row": 10,
			"end_row": 10,
			"start_col": 3,
			"end_col": 3
		},
		{
			"id": 74,
			"tex": "2 953",
			"content": [
				"2",
				"953"
			],
			"start_row": 10,
			"end_row": 10,
			"start_col": 4,
			"end_col": 4
		},
		{
			"id": 75,
			"tex": "0",
			"content": [
				"0"
			],
			"start_row": 10,
			"end_row": 10,
			"start_col": 5,
			"end_col": 5
		},
		{
			"id": 76,
			"tex": "0",
			"content": [
				"0"
			],
			"start_row": 10,
			"end_row": 10,
			"start_col": 6,
			"end_col": 6
		},
		{
			"id": 77,
			"tex": "34",
			"content": [
				"34"
			],
			"start_row": 11,
			"end_row": 11,
			"start_col": 0,
			"end_col": 0
		},
		{
			"id": 78,
			"tex": "3 833 587",
			"content": [
				"3",
				"833",
				"587"
			],
			"start_row": 11,
			"end_row": 11,
			"start_col": 1,
			"end_col": 1
		},
		{
			"id": 4,
			"tex": "$\\lambda_c \\geq 5$",
			"content": [
				"\u03bbc",
				"\u2265",
				"5"
			],
			"start_row": 0,
			"end_row": 0,
			"start_col": 4,
			"end_col": 4
		},
		{
			"id": 79,
			"tex": "0",
			"content": [
				"0"
			],
			"start_row": 11,
			"end_row": 11,
			"start_col": 2,
			"end_col": 2
		},
		{
			"id": 80,
			"tex": "0",
			"content": [
				"0"
			],
			"start_row": 11,
			"end_row": 11,
			"start_col": 3,
			"end_col": 3
		},
		{
			"id": 81,
			"tex": "19 935",
			"content": [
				"19",
				"935"
			],
			"start_row": 11,
			"end_row": 11,
			"start_col": 4,
			"end_col": 4
		},
		{
			"id": 82,
			"tex": "0",
			"content": [
				"0"
			],
			"start_row": 11,
			"end_row": 11,
			"start_col": 5,
			"end_col": 5
		},
		{
			"id": 83,
			"tex": "0",
			"content": [
				"0"
			],
			"start_row": 11,
			"end_row": 11,
			"start_col": 6,
			"end_col": 6
		},
		{
			"id": 7,
			"tex": "10",
			"content": [
				"10"
			],
			"start_row": 1,
			"end_row": 1,
			"start_col": 0,
			"end_col": 0
		},
		{
			"id": 84,
			"tex": "36",
			"content": [
				"36"
			],
			"start_row": 12,
			"end_row": 12,
			"start_col": 0,
			"end_col": 0
		},
		{
			"id": 13,
			"tex": "0",
			"content": [
				"0"
			],
			"start_row": 1,
			"end_row": 1,
			"start_col": 6,
			"end_col": 6
		},
		{
			"id": 85,
			"tex": "60 167 732",
			"content": [
				"60",
				"167",
				"732"
			],
			"start_row": 12,
			"end_row": 12,
			"start_col": 1,
			"end_col": 1
		},
		{
			"id": 86,
			"tex": "1",
			"content": [
				"1"
			],
			"start_row": 12,
			"end_row": 12,
			"start_col": 2,
			"end_col": 2
		},
		{
			"id": 87,
			"tex": "0",
			"content": [
				"0"
			],
			"start_row": 12,
			"end_row": 12,
			"start_col": 3,
			"end_col": 3
		},
		{
			"id": 88,
			"tex": "180 612",
			"content": [
				"180",
				"612"
			],
			"start_row": 12,
			"end_row": 12,
			"start_col": 4,
			"end_col": 4
		},
		{
			"id": 89,
			"tex": "1",
			"content": [
				"1"
			],
			"start_row": 12,
			"end_row": 12,
			"start_col": 5,
			"end_col": 5
		},
		{
			"id": 12,
			"tex": "0",
			"content": [
				"0"
			],
			"start_row": 1,
			"end_row": 1,
			"start_col": 5,
			"end_col": 5
		},
		{
			"id": 90,
			"tex": "1",
			"content": [
				"1"
			],
			"start_row": 12,
			"end_row": 12,
			"start_col": 6,
			"end_col": 6
		},
		{
			"id": 91,
			"tex": "38",
			"content": [
				"38"
			],
			"start_row": 13,
			"end_row": 13,
			"start_col": 0,
			"end_col": 0
		},
		{
			"id": 8,
			"tex": "1",
			"content": [
				"1"
			],
			"start_row": 1,
			"end_row": 1,
			"start_col": 1,
			"end_col": 1
		},
		{
			"id": 92,
			"tex": "$\\geq$ 19 775 768",
			"content": [
				"\u2265",
				"19",
				"775",
				"768"
			],
			"start_row": 13,
			"end_row": 13,
			"start_col": 1,
			"end_col": 1
		},
		{
			"id": 93,
			"tex": "39",
			"content": [
				"39"
			],
			"start_row": 13,
			"end_row": 13,
			"start_col": 2,
			"end_col": 2
		},
		{
			"id": 94,
			"tex": "0",
			"content": [
				"0"
			],
			"start_row": 13,
			"end_row": 13,
			"start_col": 3,
			"end_col": 3
		},
		{
			"id": 95,
			"tex": "$\\geq$ 35 429",
			"content": [
				"\u2265",
				"35",
				"429"
			],
			"start_row": 13,
			"end_row": 13,
			"start_col": 4,
			"end_col": 4
		},
		{
			"id": 11,
			"tex": "1",
			"content": [
				"1"
			],
			"start_row": 1,
			"end_row": 1,
			"start_col": 4,
			"end_col": 4
		},
		{
			"id": 96,
			"tex": "0",
			"content": [
				"0"
			],
			"start_row": 13,
			"end_row": 13,
			"start_col": 5,
			"end_col": 5
		},
		{
			"id": 9,
			"tex": "0",
			"content": [
				"0"
			],
			"start_row": 1,
			"end_row": 1,
			"start_col": 2,
			"end_col": 2
		},
		{
			"id": 97,
			"tex": "0",
			"content": [
				"0"
			],
			"start_row": 13,
			"end_row": 13,
			"start_col": 6,
			"end_col": 6
		},
		{
			"id": 98,
			"tex": "40",
			"content": [
				"40"
			],
			"start_row": 14,
			"end_row": 14,
			"start_col": 0,
			"end_col": 0
		},
		{
			"id": 14,
			"tex": "12,14,16",
			"content": [
				"12,14,16"
			],
			"start_row": 2,
			"end_row": 2,
			"start_col": 0,
			"end_col": 0
		},
		{
			"id": 99,
			"tex": "?",
			"content": [
				"?"
			],
			"start_row": 14,
			"end_row": 14,
			"start_col": 1,
			"end_col": 1
		},
		{
			"id": 3,
			"tex": "$g \\geq 7$",
			"content": [
				"g",
				"\u2265",
				"7"
			],
			"start_row": 0,
			"end_row": 0,
			"start_col": 3,
			"end_col": 3
		},
		{
			"id": 100,
			"tex": "$\\geq 25$",
			"content": [
				"\u2265",
				"25"
			],
			"start_row": 14,
			"end_row": 14,
			"start_col": 2,
			"end_col": 2
		},
		{
			"id": 101,
			"tex": "0",
			"content": [
				"0"
			],
			"start_row": 14,
			"end_row": 14,
			"start_col": 3,
			"end_col": 3
		},
		{
			"id": 102,
			"tex": "?",
			"content": [
				"?"
			],
			"start_row": 14,
			"end_row": 14,
			"start_col": 4,
			"end_col": 4
		},
		{
			"id": 103,
			"tex": "$\\geq 0$",
			"content": [
				"\u2265",
				"0"
			],
			"start_row": 14,
			"end_row": 14,
			"start_col": 5,
			"end_col": 5
		},
		{
			"id": 104,
			"tex": "?",
			"content": [
				"?"
			],
			"start_row": 14,
			"end_row": 14,
			"start_col": 6,
			"end_col": 6
		},
		{
			"id": 105,
			"tex": "42",
			"content": [
				"42"
			],
			"start_row": 15,
			"end_row": 15,
			"start_col": 0,
			"end_col": 0
		},
		{
			"id": 106,
			"tex": "?",
			"content": [
				"?"
			],
			"start_row": 15,
			"end_row": 15,
			"start_col": 1,
			"end_col": 1
		},
		{
			"id": 107,
			"tex": "?",
			"content": [
				"?"
			],
			"start_row": 15,
			"end_row": 15,
			"start_col": 2,
			"end_col": 2
		},
		{
			"id": 2,
			"tex": "$g \\geq 6$",
			"content": [
				"g",
				"\u2265",
				"6"
			],
			"start_row": 0,
			"end_row": 0,
			"start_col": 2,
			"end_col": 2
		},
		{
			"id": 108,
			"tex": "0",
			"content": [
				"0"
			],
			"start_row": 15,
			"end_row": 15,
			"start_col": 3,
			"end_col": 3
		},
		{
			"id": 109,
			"tex": "?",
			"content": [
				"?"
			],
			"start_row": 15,
			"end_row": 15,
			"start_col": 4,
			"end_col": 4
		},
		{
			"id": 110,
			"tex": "?",
			"content": [
				"?"
			],
			"start_row": 15,
			"end_row": 15,
			"start_col": 5,
			"end_col": 5
		},
		{
			"id": 111,
			"tex": "?",
			"content": [
				"?"
			],
			"start_row": 15,
			"end_row": 15,
			"start_col": 6,
			"end_col": 6
		},
		{
			"id": 0,
			"tex": "Order",
			"content": [
				"Order"
			],
			"start_row": 0,
			"end_row": 0,
			"start_col": 0,
			"end_col": 0
		},
		{
			"id": 5,
			"tex": "$\\lambda_c \\geq 5$ and $g \\geq 6$",
			"content": [
				"\u03bbc",
				"\u2265",
				"5",
				"and",
				"g",
				"\u2265",
				"6"
			],
			"start_row": 0,
			"end_row": 0,
			"start_col": 5,
			"end_col": 5
		},
		{
			"id": 15,
			"tex": "0",
			"content": [
				"0"
			],
			"start_row": 2,
			"end_row": 2,
			"start_col": 1,
			"end_col": 1
		},
		{
			"id": 44,
			"tex": "0",
			"content": [
				"0"
			],
			"start_row": 6,
			"end_row": 6,
			"start_col": 2,
			"end_col": 2
		},
		{
			"id": 43,
			"tex": "38",
			"content": [
				"38"
			],
			"start_row": 6,
			"end_row": 6,
			"start_col": 1,
			"end_col": 1
		},
		{
			"id": 42,
			"tex": "24",
			"content": [
				"24"
			],
			"start_row": 6,
			"end_row": 6,
			"start_col": 0,
			"end_col": 0
		},
		{
			"id": 41,
			"tex": "0",
			"content": [
				"0"
			],
			"start_row": 5,
			"end_row": 5,
			"start_col": 6,
			"end_col": 6
		},
		{
			"id": 40,
			"tex": "0",
			"content": [
				"0"
			],
			"start_row": 5,
			"end_row": 5,
			"start_col": 5,
			"end_col": 5
		},
		{
			"id": 39,
			"tex": "2",
			"content": [
				"2"
			],
			"start_row": 5,
			"end_row": 5,
			"start_col": 4,
			"end_col": 4
		},
		{
			"id": 38,
			"tex": "0",
			"content": [
				"0"
			],
			"start_row": 5,
			"end_row": 5,
			"start_col": 3,
			"end_col": 3
		},
		{
			"id": 37,
			"tex": "0",
			"content": [
				"0"
			],
			"start_row": 5,
			"end_row": 5,
			"start_col": 2,
			"end_col": 2
		},
		{
			"id": 36,
			"tex": "20",
			"content": [
				"20"
			],
			"start_row": 5,
			"end_row": 5,
			"start_col": 1,
			"end_col": 1
		},
		{
			"id": 35,
			"tex": "22",
			"content": [
				"22"
			],
			"start_row": 5,
			"end_row": 5,
			"start_col": 0,
			"end_col": 0
		},
		{
			"id": 34,
			"tex": "0",
			"content": [
				"0"
			],
			"start_row": 4,
			"end_row": 4,
			"start_col": 6,
			"end_col": 6
		},
		{
			"id": 33,
			"tex": "0",
			"content": [
				"0"
			],
			"start_row": 4,
			"end_row": 4,
			"start_col": 5,
			"end_col": 5
		},
		{
			"id": 32,
			"tex": "1",
			"content": [
				"1"
			],
			"start_row": 4,
			"end_row": 4,
			"start_col": 4,
			"end_col": 4
		},
		{
			"id": 31,
			"tex": "0",
			"content": [
				"0"
			],
			"start_row": 4,
			"end_row": 4,
			"start_col": 3,
			"end_col": 3
		},
		{
			"id": 30,
			"tex": "0",
			"content": [
				"0"
			],
			"start_row": 4,
			"end_row": 4,
			"start_col": 2,
			"end_col": 2
		},
		{
			"id": 29,
			"tex": "6",
			"content": [
				"6"
			],
			"start_row": 4,
			"end_row": 4,
			"start_col": 1,
			"end_col": 1
		},
		{
			"id": 28,
			"tex": "20",
			"content": [
				"20"
			],
			"start_row": 4,
			"end_row": 4,
			"start_col": 0,
			"end_col": 0
		},
		{
			"id": 27,
			"tex": "0",
			"content": [
				"0"
			],
			"start_row": 3,
			"end_row": 3,
			"start_col": 6,
			"end_col": 6
		},
		{
			"id": 26,
			"tex": "0",
			"content": [
				"0"
			],
			"start_row": 3,
			"end_row": 3,
			"start_col": 5,
			"end_col": 5
		},
		{
			"id": 25,
			"tex": "0",
			"content": [
				"0"
			],
			"start_row": 3,
			"end_row": 3,
			"start_col": 4,
			"end_col": 4
		},
		{
			"id": 24,
			"tex": "0",
			"content": [
				"0"
			],
			"start_row": 3,
			"end_row": 3,
			"start_col": 3,
			"end_col": 3
		},
		{
			"id": 23,
			"tex": "0",
			"content": [
				"0"
			],
			"start_row": 3,
			"end_row": 3,
			"start_col": 2,
			"end_col": 2
		},
		{
			"id": 22,
			"tex": "2",
			"content": [
				"2"
			],
			"start_row": 3,
			"end_row": 3,
			"start_col": 1,
			"end_col": 1
		},
		{
			"id": 21,
			"tex": "18",
			"content": [
				"18"
			],
			"start_row": 3,
			"end_row": 3,
			"start_col": 0,
			"end_col": 0
		},
		{
			"id": 20,
			"tex": "0",
			"content": [
				"0"
			],
			"start_row": 2,
			"end_row": 2,
			"start_col": 6,
			"end_col": 6
		},
		{
			"id": 19,
			"tex": "0",
			"content": [
				"0"
			],
			"start_row": 2,
			"end_row": 2,
			"start_col": 5,
			"end_col": 5
		},
		{
			"id": 18,
			"tex": "0",
			"content": [
				"0"
			],
			"start_row": 2,
			"end_row": 2,
			"start_col": 4,
			"end_col": 4
		},
		{
			"id": 17,
			"tex": "0",
			"content": [
				"0"
			],
			"start_row": 2,
			"end_row": 2,
			"start_col": 3,
			"end_col": 3
		},
		{
			"id": 16,
			"tex": "0",
			"content": [
				"0"
			],
			"start_row": 2,
			"end_row": 2,
			"start_col": 2,
			"end_col": 2
		},
		{
			"id": 45,
			"tex": "0",
			"content": [
				"0"
			],
			"start_row": 6,
			"end_row": 6,
			"start_col": 3,
			"end_col": 3
		},
		{
			"id": 46,
			"tex": "2",
			"content": [
				"2"
			],
			"start_row": 6,
			"end_row": 6,
			"start_col": 4,
			"end_col": 4
		},
		{
			"id": 47,
			"tex": "0",
			"content": [
				"0"
			],
			"start_row": 6,
			"end_row": 6,
			"start_col": 5,
			"end_col": 5
		},
		{
			"id": 48,
			"tex": "0",
			"content": [
				"0"
			],
			"start_row": 6,
			"end_row": 6,
			"start_col": 6,
			"end_col": 6
		},
		{
			"id": 49,
			"tex": "26",
			"content": [
				"26"
			],
			"start_row": 7,
			"end_row": 7,
			"start_col": 0,
			"end_col": 0
		},
		{
			"id": 50,
			"tex": "280",
			"content": [
				"280"
			],
			"start_row": 7,
			"end_row": 7,
			"start_col": 1,
			"end_col": 1
		},
		{
			"id": 51,
			"tex": "0",
			"content": [
				"0"
			],
			"start_row": 7,
			"end_row": 7,
			"start_col": 2,
			"end_col": 2
		},
		{
			"id": 52,
			"tex": "0",
			"content": [
				"0"
			],
			"start_row": 7,
			"end_row": 7,
			"start_col": 3,
			"end_col": 3
		},
		{
			"id": 53,
			"tex": "10",
			"content": [
				"10"
			],
			"start_row": 7,
			"end_row": 7,
			"start_col": 4,
			"end_col": 4
		},
		{
			"id": 54,
			"tex": "0",
			"content": [
				"0"
			],
			"start_row": 7,
			"end_row": 7,
			"start_col": 5,
			"end_col": 5
		},
		{
			"id": 55,
			"tex": "0",
			"content": [
				"0"
			],
			"start_row": 7,
			"end_row": 7,
			"start_col": 6,
			"end_col": 6
		},
		{
			"id": 56,
			"tex": "28",
			"content": [
				"28"
			],
			"start_row": 8,
			"end_row": 8,
			"start_col": 0,
			"end_col": 0
		},
		{
			"id": 57,
			"tex": "2 900",
			"content": [
				"2",
				"900"
			],
			"start_row": 8,
			"end_row": 8,
			"start_col": 1,
			"end_col": 1
		},
		{
			"id": 58,
			"tex": "1",
			"content": [
				"1"
			],
			"start_row": 8,
			"end_row": 8,
			"start_col": 2,
			"end_col": 2
		},
		{
			"id": 59,
			"tex": "0",
			"content": [
				"0"
			],
			"start_row": 8,
			"end_row": 8,
			"start_col": 3,
			"end_col": 3
		}
	]
}