{
	"cells": [
		{
			"id": 4,
			"tex": "picture",
			"content": [
				"picture"
			],
			"start_row": 2,
			"end_row": 2,
			"start_col": 0,
			"end_col": 0
		},
		{
			"id": 0,
			"tex": "Digital Watermarking",
			"content": [
				"Digital",
				"Watermarking"
			],
			"start_row": 0,
			"end_row": 0,
			"start_col": 0,
			"end_col": 0
		},
		{
			"id": 15,
			"tex": "signal attenuation",
			"content": [
				"signal",
				"attenuation"
			],
			"start_row": 7,
			"end_row": 7,
			"start_col": 1,
			"end_col": 1
		},
		{
			"id": 5,
			"tex": "network",
			"content": [
				"network"
			],
			"start_row": 2,
			"end_row": 2,
			"start_col": 1,
			"end_col": 1
		},
		{
			"id": 12,
			"tex": "contrast attacks",
			"content": [
				"contrast",
				"attacks"
			],
			"start_row": 6,
			"end_row": 6,
			"start_col": 0,
			"end_col": 0
		},
		{
			"id": 3,
			"tex": "node",
			"content": [
				"node"
			],
			"start_row": 1,
			"end_row": 1,
			"start_col": 1,
			"end_col": 1
		},
		{
			"id": 11,
			"tex": "transmission errors",
			"content": [
				"transmission",
				"errors"
			],
			"start_row": 5,
			"end_row": 5,
			"start_col": 1,
			"end_col": 1
		},
		{
			"id": 6,
			"tex": "zeroing attack",
			"content": [
				"zeroing",
				"attack"
			],
			"start_row": 3,
			"end_row": 3,
			"start_col": 0,
			"end_col": 0
		},
		{
			"id": 14,
			"tex": "blur attacks",
			"content": [
				"blur",
				"attacks"
			],
			"start_row": 7,
			"end_row": 7,
			"start_col": 0,
			"end_col": 0
		},
		{
			"id": 2,
			"tex": "pixel",
			"content": [
				"pixel"
			],
			"start_row": 1,
			"end_row": 1,
			"start_col": 0,
			"end_col": 0
		},
		{
			"id": 10,
			"tex": "uniform or gaussian noise",
			"content": [
				"uniform",
				"or",
				"gaussian",
				"noise"
			],
			"start_row": 5,
			"end_row": 5,
			"start_col": 0,
			"end_col": 0
		},
		{
			"id": 1,
			"tex": "WSN",
			"content": [
				"WSN"
			],
			"start_row": 0,
			"end_row": 0,
			"start_col": 1,
			"end_col": 1
		},
		{
			"id": 9,
			"tex": "nodes displacement",
			"content": [
				"nodes",
				"displacement"
			],
			"start_row": 4,
			"end_row": 4,
			"start_col": 1,
			"end_col": 1
		},
		{
			"id": 13,
			"tex": "unbalanced signals",
			"content": [
				"unbalanced",
				"signals"
			],
			"start_row": 6,
			"end_row": 6,
			"start_col": 1,
			"end_col": 1
		},
		{
			"id": 8,
			"tex": "rotation and resize attacks",
			"content": [
				"rotation",
				"and",
				"resize",
				"attacks"
			],
			"start_row": 4,
			"end_row": 4,
			"start_col": 0,
			"end_col": 0
		},
		{
			"id": 7,
			"tex": "death of nodes",
			"content": [
				"death",
				"of",
				"nodes"
			],
			"start_row": 3,
			"end_row": 3,
			"start_col": 1,
			"end_col": 1
		}
	]
}