{
	"cells": [
		{
			"id": 15,
			"tex": "7",
			"content": [
				"7"
			],
			"start_row": 2,
			"end_row": 2,
			"start_col": 1,
			"end_col": 1
		},
		{
			"id": 6,
			"tex": "\\textbf{DFS}",
			"content": [
				"DFS"
			],
			"start_row": 0,
			"end_row": 0,
			"start_col": 6,
			"end_col": 6
		},
		{
			"id": 8,
			"tex": "4",
			"content": [
				"4"
			],
			"start_row": 1,
			"end_row": 1,
			"start_col": 1,
			"end_col": 1
		},
		{
			"id": 24,
			"tex": "7.2 GB",
			"content": [
				"7.2",
				"GB"
			],
			"start_row": 3,
			"end_row": 3,
			"start_col": 3,
			"end_col": 3
		},
		{
			"id": 2,
			"tex": "\\textbf{$\\sharp$ columns}",
			"content": [
				"(cid:93)",
				"columns"
			],
			"start_row": 0,
			"end_row": 0,
			"start_col": 2,
			"end_col": 2
		},
		{
			"id": 34,
			"tex": "(not finished)",
			"content": [
				"(not",
				"\ufb01nished)"
			],
			"start_row": 4,
			"end_row": 4,
			"start_col": 6,
			"end_col": 6
		},
		{
			"id": 7,
			"tex": "KDD Cup 2014",
			"content": [
				"KDD",
				"Cup",
				"2014"
			],
			"start_row": 1,
			"end_row": 1,
			"start_col": 0,
			"end_col": 0
		},
		{
			"id": 26,
			"tex": "1 week",
			"content": [
				"1",
				"week"
			],
			"start_row": 3,
			"end_row": 3,
			"start_col": 5,
			"end_col": 5
		},
		{
			"id": 14,
			"tex": "Coupon purchase",
			"content": [
				"Coupon",
				"purchase"
			],
			"start_row": 2,
			"end_row": 2,
			"start_col": 0,
			"end_col": 0
		},
		{
			"id": 16,
			"tex": "50",
			"content": [
				"50"
			],
			"start_row": 2,
			"end_row": 2,
			"start_col": 2,
			"end_col": 2
		},
		{
			"id": 11,
			"tex": "12.9 h",
			"content": [
				"12.9",
				"h"
			],
			"start_row": 1,
			"end_row": 1,
			"start_col": 4,
			"end_col": 4
		},
		{
			"id": 12,
			"tex": "1 week",
			"content": [
				"1",
				"week"
			],
			"start_row": 1,
			"end_row": 1,
			"start_col": 5,
			"end_col": 5
		},
		{
			"id": 23,
			"tex": "19",
			"content": [
				"19"
			],
			"start_row": 3,
			"end_row": 3,
			"start_col": 2,
			"end_col": 2
		},
		{
			"id": 0,
			"tex": "\\textbf{Data}",
			"content": [
				"Data"
			],
			"start_row": 0,
			"end_row": 0,
			"start_col": 0,
			"end_col": 0
		},
		{
			"id": 22,
			"tex": "5",
			"content": [
				"5"
			],
			"start_row": 3,
			"end_row": 3,
			"start_col": 1,
			"end_col": 1
		},
		{
			"id": 27,
			"tex": "2 weeks",
			"content": [
				"2",
				"weeks"
			],
			"start_row": 3,
			"end_row": 3,
			"start_col": 6,
			"end_col": 6
		},
		{
			"id": 32,
			"tex": "",
			"content": [],
			"start_row": 4,
			"end_row": 4,
			"start_col": 4,
			"end_col": 4
		},
		{
			"id": 10,
			"tex": "0.9 GB",
			"content": [
				"0.9",
				"GB"
			],
			"start_row": 1,
			"end_row": 1,
			"start_col": 3,
			"end_col": 3
		},
		{
			"id": 4,
			"tex": "\\textbf{OneBM}",
			"content": [
				"OneBM"
			],
			"start_row": 0,
			"end_row": 0,
			"start_col": 4,
			"end_col": 4
		},
		{
			"id": 33,
			"tex": "",
			"content": [],
			"start_row": 4,
			"end_row": 4,
			"start_col": 5,
			"end_col": 5
		},
		{
			"id": 19,
			"tex": "1 week",
			"content": [
				"1",
				"week"
			],
			"start_row": 2,
			"end_row": 2,
			"start_col": 5,
			"end_col": 5
		},
		{
			"id": 1,
			"tex": "\\textbf{$\\sharp$ tables}",
			"content": [
				"(cid:93)",
				"tables"
			],
			"start_row": 0,
			"end_row": 0,
			"start_col": 1,
			"end_col": 1
		},
		{
			"id": 25,
			"tex": "56 min.",
			"content": [
				"56",
				"min."
			],
			"start_row": 3,
			"end_row": 3,
			"start_col": 4,
			"end_col": 4
		},
		{
			"id": 3,
			"tex": "\\textbf{size}",
			"content": [
				"size"
			],
			"start_row": 0,
			"end_row": 0,
			"start_col": 3,
			"end_col": 3
		},
		{
			"id": 9,
			"tex": "51",
			"content": [
				"51"
			],
			"start_row": 1,
			"end_row": 1,
			"start_col": 2,
			"end_col": 2
		},
		{
			"id": 28,
			"tex": "",
			"content": [],
			"start_row": 4,
			"end_row": 4,
			"start_col": 0,
			"end_col": 0
		},
		{
			"id": 31,
			"tex": "",
			"content": [],
			"start_row": 4,
			"end_row": 4,
			"start_col": 3,
			"end_col": 3
		},
		{
			"id": 21,
			"tex": "Grupo Bimbo",
			"content": [
				"Grupo",
				"Bimbo"
			],
			"start_row": 3,
			"end_row": 3,
			"start_col": 0,
			"end_col": 0
		},
		{
			"id": 18,
			"tex": "2.8 h",
			"content": [
				"2.8",
				"h"
			],
			"start_row": 2,
			"end_row": 2,
			"start_col": 4,
			"end_col": 4
		},
		{
			"id": 17,
			"tex": "2.2 GB",
			"content": [
				"2.2",
				"GB"
			],
			"start_row": 2,
			"end_row": 2,
			"start_col": 3,
			"end_col": 3
		},
		{
			"id": 13,
			"tex": "NA",
			"content": [
				"NA"
			],
			"start_row": 1,
			"end_row": 1,
			"start_col": 6,
			"end_col": 6
		},
		{
			"id": 20,
			"tex": "84.04 hours",
			"content": [
				"84.04",
				"hours"
			],
			"start_row": 2,
			"end_row": 2,
			"start_col": 6,
			"end_col": 6
		},
		{
			"id": 5,
			"tex": "\\textbf{r2n}",
			"content": [
				"r2n"
			],
			"start_row": 0,
			"end_row": 0,
			"start_col": 5,
			"end_col": 5
		},
		{
			"id": 29,
			"tex": "",
			"content": [],
			"start_row": 4,
			"end_row": 4,
			"start_col": 1,
			"end_col": 1
		},
		{
			"id": 30,
			"tex": "",
			"content": [],
			"start_row": 4,
			"end_row": 4,
			"start_col": 2,
			"end_col": 2
		}
	]
}