{
	"cells": [
		{
			"id": 8,
			"tex": "15.22",
			"content": [
				"15.22"
			],
			"start_row": 2,
			"end_row": 2,
			"start_col": 2,
			"end_col": 2
		},
		{
			"id": 9,
			"tex": "1 Ref. Human",
			"content": [
				"1",
				"Ref.",
				"Human"
			],
			"start_row": 3,
			"end_row": 3,
			"start_col": 0,
			"end_col": 0
		},
		{
			"id": 2,
			"tex": "Metro",
			"content": [
				"Metro"
			],
			"start_row": 0,
			"end_row": 0,
			"start_col": 2,
			"end_col": 2
		},
		{
			"id": 0,
			"tex": "",
			"content": [],
			"start_row": 0,
			"end_row": 0,
			"start_col": 0,
			"end_col": 0
		},
		{
			"id": 10,
			"tex": "16.39",
			"content": [
				"16.39"
			],
			"start_row": 3,
			"end_row": 3,
			"start_col": 1,
			"end_col": 1
		},
		{
			"id": 11,
			"tex": "13.46",
			"content": [
				"13.46"
			],
			"start_row": 3,
			"end_row": 3,
			"start_col": 2,
			"end_col": 2
		},
		{
			"id": 6,
			"tex": "1 Sphere",
			"content": [
				"1",
				"Sphere"
			],
			"start_row": 2,
			"end_row": 2,
			"start_col": 0,
			"end_col": 0
		},
		{
			"id": 1,
			"tex": "Chamfer",
			"content": [
				"Chamfer"
			],
			"start_row": 0,
			"end_row": 0,
			"start_col": 1,
			"end_col": 1
		},
		{
			"id": 7,
			"tex": "15.78",
			"content": [
				"15.78"
			],
			"start_row": 2,
			"end_row": 2,
			"start_col": 1,
			"end_col": 1
		},
		{
			"id": 5,
			"tex": "11.62",
			"content": [
				"11.62"
			],
			"start_row": 1,
			"end_row": 1,
			"start_col": 2,
			"end_col": 2
		},
		{
			"id": 4,
			"tex": "15.47",
			"content": [
				"15.47"
			],
			"start_row": 1,
			"end_row": 1,
			"start_col": 1,
			"end_col": 1
		},
		{
			"id": 3,
			"tex": "25 patches",
			"content": [
				"25",
				"patches"
			],
			"start_row": 1,
			"end_row": 1,
			"start_col": 0,
			"end_col": 0
		}
	]
}