{
	"cells": [
		{
			"id": 1,
			"tex": "\\textbf{accu.}",
			"content": [
				"accu."
			],
			"start_row": 0,
			"end_row": 0,
			"start_col": 1,
			"end_col": 1
		},
		{
			"id": 21,
			"tex": "\\textbf{74.1}",
			"content": [
				"74.1"
			],
			"start_row": 4,
			"end_row": 4,
			"start_col": 1,
			"end_col": 1
		},
		{
			"id": 7,
			"tex": "73.6",
			"content": [
				"73.6"
			],
			"start_row": 1,
			"end_row": 1,
			"start_col": 2,
			"end_col": 2
		},
		{
			"id": 6,
			"tex": "73.4",
			"content": [
				"73.4"
			],
			"start_row": 1,
			"end_row": 1,
			"start_col": 1,
			"end_col": 1
		},
		{
			"id": 10,
			"tex": "LSTM w/ attention",
			"content": [
				"LSTM",
				"w/",
				"attention"
			],
			"start_row": 2,
			"end_row": 2,
			"start_col": 0,
			"end_col": 0
		},
		{
			"id": 0,
			"tex": "\\textbf{method}",
			"content": [
				"method"
			],
			"start_row": 0,
			"end_row": 0,
			"start_col": 0,
			"end_col": 0
		},
		{
			"id": 23,
			"tex": "\\textbf{75.0}",
			"content": [
				"75.0"
			],
			"start_row": 4,
			"end_row": 4,
			"start_col": 3,
			"end_col": 3
		},
		{
			"id": 24,
			"tex": "\\textbf{74.3}",
			"content": [
				"74.3"
			],
			"start_row": 4,
			"end_row": 4,
			"start_col": 4,
			"end_col": 4
		},
		{
			"id": 9,
			"tex": "73.4",
			"content": [
				"73.4"
			],
			"start_row": 1,
			"end_row": 1,
			"start_col": 4,
			"end_col": 4
		},
		{
			"id": 13,
			"tex": "72.5",
			"content": [
				"72.5"
			],
			"start_row": 2,
			"end_row": 2,
			"start_col": 3,
			"end_col": 3
		},
		{
			"id": 12,
			"tex": "74.4",
			"content": [
				"74.4"
			],
			"start_row": 2,
			"end_row": 2,
			"start_col": 2,
			"end_col": 2
		},
		{
			"id": 14,
			"tex": "73.4",
			"content": [
				"73.4"
			],
			"start_row": 2,
			"end_row": 2,
			"start_col": 4,
			"end_col": 4
		},
		{
			"id": 5,
			"tex": "LSTM",
			"content": [
				"LSTM"
			],
			"start_row": 1,
			"end_row": 1,
			"start_col": 0,
			"end_col": 0
		},
		{
			"id": 15,
			"tex": "BLSTM",
			"content": [
				"BLSTM"
			],
			"start_row": 3,
			"end_row": 3,
			"start_col": 0,
			"end_col": 0
		},
		{
			"id": 11,
			"tex": "73.8",
			"content": [
				"73.8"
			],
			"start_row": 2,
			"end_row": 2,
			"start_col": 1,
			"end_col": 1
		},
		{
			"id": 22,
			"tex": "73.6",
			"content": [
				"73.6"
			],
			"start_row": 4,
			"end_row": 4,
			"start_col": 2,
			"end_col": 2
		},
		{
			"id": 2,
			"tex": "\\textbf{prec.}",
			"content": [
				"prec."
			],
			"start_row": 0,
			"end_row": 0,
			"start_col": 2,
			"end_col": 2
		},
		{
			"id": 17,
			"tex": "\\textbf{74.7}",
			"content": [
				"74.7"
			],
			"start_row": 3,
			"end_row": 3,
			"start_col": 2,
			"end_col": 2
		},
		{
			"id": 19,
			"tex": "73.2",
			"content": [
				"73.2"
			],
			"start_row": 3,
			"end_row": 3,
			"start_col": 4,
			"end_col": 4
		},
		{
			"id": 20,
			"tex": "BLSTM w/ attention",
			"content": [
				"BLSTM",
				"w/",
				"attention"
			],
			"start_row": 4,
			"end_row": 4,
			"start_col": 0,
			"end_col": 0
		},
		{
			"id": 16,
			"tex": "73.8",
			"content": [
				"73.8"
			],
			"start_row": 3,
			"end_row": 3,
			"start_col": 1,
			"end_col": 1
		},
		{
			"id": 3,
			"tex": "\\textbf{recall}",
			"content": [
				"recall"
			],
			"start_row": 0,
			"end_row": 0,
			"start_col": 3,
			"end_col": 3
		},
		{
			"id": 8,
			"tex": "73.1",
			"content": [
				"73.1"
			],
			"start_row": 1,
			"end_row": 1,
			"start_col": 3,
			"end_col": 3
		},
		{
			"id": 18,
			"tex": "71.9",
			"content": [
				"71.9"
			],
			"start_row": 3,
			"end_row": 3,
			"start_col": 3,
			"end_col": 3
		},
		{
			"id": 4,
			"tex": "\\textbf{f-score}",
			"content": [
				"f-score"
			],
			"start_row": 0,
			"end_row": 0,
			"start_col": 4,
			"end_col": 4
		}
	]
}