{
	"cells": [
		{
			"id": 3,
			"tex": "chi1",
			"content": [
				"chi1"
			],
			"start_row": 0,
			"end_row": 0,
			"start_col": 3,
			"end_col": 3
		},
		{
			"id": 9,
			"tex": "eat",
			"content": [
				"eat"
			],
			"start_row": 1,
			"end_row": 1,
			"start_col": 3,
			"end_col": 3
		},
		{
			"id": 1,
			"tex": "dao4",
			"content": [
				"dao4"
			],
			"start_row": 0,
			"end_row": 0,
			"start_col": 1,
			"end_col": 1
		},
		{
			"id": 11,
			"tex": "meal",
			"content": [
				"meal"
			],
			"start_row": 1,
			"end_row": 1,
			"start_col": 5,
			"end_col": 5
		},
		{
			"id": 0,
			"tex": "Chinese",
			"content": [
				"Chinese"
			],
			"start_row": 0,
			"end_row": 0,
			"start_col": 0,
			"end_col": 0
		},
		{
			"id": 6,
			"tex": "Meaning",
			"content": [
				"Meaning"
			],
			"start_row": 1,
			"end_row": 1,
			"start_col": 0,
			"end_col": 0
		},
		{
			"id": 8,
			"tex": "home",
			"content": [
				"home"
			],
			"start_row": 1,
			"end_row": 1,
			"start_col": 2,
			"end_col": 2
		},
		{
			"id": 7,
			"tex": "go",
			"content": [
				"go"
			],
			"start_row": 1,
			"end_row": 1,
			"start_col": 1,
			"end_col": 1
		},
		{
			"id": 4,
			"tex": "dun4",
			"content": [
				"dun4"
			],
			"start_row": 0,
			"end_row": 0,
			"start_col": 4,
			"end_col": 4
		},
		{
			"id": 10,
			"tex": "a",
			"content": [
				"a"
			],
			"start_row": 1,
			"end_row": 1,
			"start_col": 4,
			"end_col": 4
		},
		{
			"id": 5,
			"tex": "fan4",
			"content": [
				"fan4"
			],
			"start_row": 0,
			"end_row": 0,
			"start_col": 5,
			"end_col": 5
		},
		{
			"id": 2,
			"tex": "jia1 li2",
			"content": [
				"jia1",
				"li2"
			],
			"start_row": 0,
			"end_row": 0,
			"start_col": 2,
			"end_col": 2
		}
	]
}